[{
  "videoWebUrl": "https://www.tiktok.com/@lizplank/video/7373467232476663083",
  "submittedVideoUrl": "https://www.tiktok.com/@lizplank/video/7373467232476663083",
  "cid": "7373493359149417246",
  "createTime": 1716775220,
  "createTimeISO": "2024-05-27T02:00:20.000Z",
  "text": "Ooo what pants are those???",
  "diggCount": 10,
  "repliesToId": null,
  "replyCommentTotal": 3,
  "uid": "6713203630369997830",
  "uniqueId": "albany.and.avers",
  "avatarThumbnail": "https://p16-sign-va.tiktokcdn.com/tos-maliva-avt-0068/abc886d1ea47115977c016553dc0c930~c5_100x100.jpg?lk3s=30310797&nonce=36498&refresh_token=19597e8c8111229ad07076b05106afdd&x-expires=1735113600&x-signature=59WIVxBasbBVi549yTOsx%2BSwxok%3D&shp=30310797&shcp=-"
},
{
  "videoWebUrl": "https://www.tiktok.com/@lizplank/video/7373467232476663083",
  "submittedVideoUrl": "https://www.tiktok.com/@lizplank/video/7373467232476663083",
  "cid": "7373657188102062890",
  "createTime": 1716813414,
  "createTimeISO": "2024-05-27T12:36:54.000Z",
  "text": "adidas!!",
  "diggCount": 1,
  "repliesToId": "7373493359149417246",
  "replyCommentTotal": null,
  "uid": "6638019241584410630",
  "uniqueId": "lizplank",
  "avatarThumbnail": "https://p16-sign-va.tiktokcdn.com/tos-maliva-avt-0068/7328630067771211822~c5_100x100.jpg?lk3s=30310797&nonce=16464&refresh_token=de90bb51416527bddb0eaca0147d06d3&x-expires=1735113600&x-signature=NQS3VJd41ms%2BOV8xTGSBVgrCDo8%3D&shp=30310797&shcp=-"
},
{
  "videoWebUrl": "https://www.tiktok.com/@lizplank/video/7373467232476663083",
  "submittedVideoUrl": "https://www.tiktok.com/@lizplank/video/7373467232476663083",
  "cid": "7373538879206015790",
  "createTime": 1716785830,
  "createTimeISO": "2024-05-27T04:57:10.000Z",
  "text": "I would love to accidentally photobomb you ✨😂💚",
  "diggCount": 3,
  "repliesToId": null,
  "replyCommentTotal": 2,
  "uid": "6839388255630476293",
  "uniqueId": "biancadoesnyc",
  "avatarThumbnail": "https://p16-sign-va.tiktokcdn.com/tos-maliva-avt-0068/a163562072d03d70390fba7d0b92b531~c5_100x100.jpg?lk3s=30310797&nonce=7400&refresh_token=24cbac068e98fa73f5c31ed72e24cb43&x-expires=1735113600&x-signature=bBM0PsuzsSdAaOopWwYeITpqybA%3D&shp=30310797&shcp=-"
},
{
  "videoWebUrl": "https://www.tiktok.com/@lizplank/video/7373467232476663083",
  "submittedVideoUrl": "https://www.tiktok.com/@lizplank/video/7373467232476663083",
  "cid": "7373657372227257131",
  "createTime": 1716813444,
  "createTimeISO": "2024-05-27T12:37:24.000Z",
  "text": "we were dying to have someone like you join us!!",
  "diggCount": 1,
  "repliesToId": "7373538879206015790",
  "replyCommentTotal": null,
  "uid": "6638019241584410630",
  "uniqueId": "lizplank",
  "avatarThumbnail": "https://p16-sign-va.tiktokcdn.com/tos-maliva-avt-0068/7328630067771211822~c5_100x100.jpg?lk3s=30310797&nonce=16464&refresh_token=de90bb51416527bddb0eaca0147d06d3&x-expires=1735113600&x-signature=NQS3VJd41ms%2BOV8xTGSBVgrCDo8%3D&shp=30310797&shcp=-"
},
{
  "videoWebUrl": "https://www.tiktok.com/@lizplank/video/7373467232476663083",
  "submittedVideoUrl": "https://www.tiktok.com/@lizplank/video/7373467232476663083",
  "cid": "7373469130561520430",
  "createTime": 1716769595,
  "createTimeISO": "2024-05-27T00:26:35.000Z",
  "text": "The butterfly jumpsuit is so cute ❤️",
  "diggCount": 6,
  "repliesToId": null,
  "replyCommentTotal": 0,
  "uid": "7169747249009378347",
  "uniqueId": "ssshann_nnanigans",
  "avatarThumbnail": "https://p16-sign-va.tiktokcdn.com/tos-maliva-avt-0068/6dc100049ca212778224305494897524~c5_100x100.jpg?lk3s=30310797&nonce=10414&refresh_token=f53cfb3dd505894c262f1fdc4ab5fc5b&x-expires=1735113600&x-signature=TE3P3x3tNy91NGetTvEHKOsSlDc%3D&shp=30310797&shcp=-"
},
{
  "videoWebUrl": "https://www.tiktok.com/@lizplank/video/7373467232476663083",
  "submittedVideoUrl": "https://www.tiktok.com/@lizplank/video/7373467232476663083",
  "cid": "7373487020897846047",
  "createTime": 1716773744,
  "createTimeISO": "2024-05-27T01:35:44.000Z",
  "text": "What 😭",
  "diggCount": 0,
  "repliesToId": null,
  "replyCommentTotal": 0,
  "uid": "6795163597826081798",
  "uniqueId": "ferociouskatie",
  "avatarThumbnail": "https://p16-sign-va.tiktokcdn.com/tos-maliva-avt-0068/103a41a43920f88d5b81af38b252b6da~c5_100x100.jpg?lk3s=30310797&nonce=13387&refresh_token=cdb79c393dd725e797891d24837b0d3e&x-expires=1735113600&x-signature=4oi0pKmSTb7ZiMBcpgNJbBPcJP0%3D&shp=30310797&shcp=-"
},
{
  "videoWebUrl": "https://www.tiktok.com/@lizplank/video/7373467232476663083",
  "submittedVideoUrl": "https://www.tiktok.com/@lizplank/video/7373467232476663083",
  "cid": "7373695655607616288",
  "createTime": 1716822336,
  "createTimeISO": "2024-05-27T15:05:36.000Z",
  "text": "Please make a video for me please",
  "diggCount": 0,
  "repliesToId": "7373493359149417246",
  "replyCommentTotal": null,
  "uid": "7345649325399688224",
  "uniqueId": "randa.esaam",
  "avatarThumbnail": "https://p16-sign-useast2a.tiktokcdn.com/tos-useast2a-avt-0068-euttp/1ac43b5f21b44881aef093c7dd8b9127~c5_100x100.jpg?lk3s=30310797&nonce=45747&refresh_token=184b03ab76d980c8fa98b72af3dab573&x-expires=1735113600&x-signature=%2BlyeH4mhEU3NViel1RAZV82Q6Xc%3D&shp=30310797&shcp=-"
},
{
  "videoWebUrl": "https://www.tiktok.com/@lizplank/video/7373467232476663083",
  "submittedVideoUrl": "https://www.tiktok.com/@lizplank/video/7373467232476663083",
  "cid": "7373668080033137439",
  "createTime": 1716815904,
  "createTimeISO": "2024-05-27T13:18:24.000Z",
  "text": "lol but what’s the style name? I can’t seem to find them",
  "diggCount": 0,
  "repliesToId": "7373493359149417246",
  "replyCommentTotal": null,
  "uid": "6713203630369997830",
  "uniqueId": "albany.and.avers",
  "avatarThumbnail": "https://p19-pu-sign-useast8.tiktokcdn-us.com/tos-useast5-avt-0068-tx/abc886d1ea47115977c016553dc0c930~c5_100x100.jpg?lk3s=30310797&nonce=53989&refresh_token=00cabbb336833b818ed4782cdea13917&x-expires=1735113600&x-signature=FLgvll8f5kpPmmH%2Bp2IOBi8u0nM%3D&shp=30310797&shcp=-"
},
{
  "videoWebUrl": "https://www.tiktok.com/@lizplank/video/7373467232476663083",
  "submittedVideoUrl": "https://www.tiktok.com/@lizplank/video/7373467232476663083",
  "cid": "7373661232874439467",
  "createTime": 1716814342,
  "createTimeISO": "2024-05-27T12:52:22.000Z",
  "text": "Here I come! 💃🏻💃🏻💃🏻",
  "diggCount": 1,
  "repliesToId": "7373538879206015790",
  "replyCommentTotal": null,
  "uid": "6839388255630476293",
  "uniqueId": "biancadoesnyc",
  "avatarThumbnail": "https://p19-pu-sign-useast8.tiktokcdn-us.com/tos-useast5-avt-0068-tx/a163562072d03d70390fba7d0b92b531~c5_100x100.jpg?lk3s=30310797&nonce=73585&refresh_token=7eb909b35d7584450bedd9657fb5a244&x-expires=1735113600&x-signature=dDj%2FzWQXykO8ApQBeMA6lCIoVqs%3D&shp=30310797&shcp=-"
}]