[{
  "videoWebUrl": "https://www.tiktok.com/@itsme_lisap/video/7390393988332801326",
  "submittedVideoUrl": "https://www.tiktok.com/@itsme_lisap/video/7390393988332801326",
  "cid": "7390395348642562847",
  "createTime": 1720710535,
  "createTimeISO": "2024-07-11T15:08:55.000Z",
  "text": "Gorgeous 🤌as always",
  "diggCount": 1,
  "repliesToId": null,
  "replyCommentTotal": 0,
  "uid": "6845378914413151238",
  "uniqueId": "sboykin10",
  "avatarThumbnail": "https://p16-sign-va.tiktokcdn.com/tos-maliva-avt-0068/e65a86a467c89bcf4657ebd71ba2c60b~c5_100x100.jpg?lk3s=30310797&nonce=98391&refresh_token=9d2cc6bf8646d106bf00cd3cce1430ce&x-expires=1737291600&x-signature=Y2W%2BqRb0XeVu7NbckcK9a88Jwn4%3D&shp=30310797&shcp=-"
},
{
  "videoWebUrl": "https://www.tiktok.com/@itsme_lisap/video/7390393988332801326",
  "submittedVideoUrl": "https://www.tiktok.com/@itsme_lisap/video/7390393988332801326",
  "cid": "7390941819347338014",
  "createTime": 1720837764,
  "createTimeISO": "2024-07-13T02:29:24.000Z",
  "text": "Any Botox for you as of yet. Just asking.",
  "diggCount": 0,
  "repliesToId": null,
  "replyCommentTotal": 0,
  "uid": "6822443958929769477",
  "uniqueId": "justforfun81200",
  "avatarThumbnail": "https://p19-pu-sign-useast8.tiktokcdn-us.com/tos-useast5-avt-0068-tx/b456381418a123169669abd236711f71~c5_100x100.jpg?lk3s=30310797&nonce=76220&refresh_token=61d6d11a97f6b8ebe41308f38014fc64&x-expires=1737291600&x-signature=UruAeGKtwX1yAlHarynu%2BcTVxlM%3D&shp=30310797&shcp=-"
}]