[{
  "videoWebUrl": "https://www.tiktok.com/@itsme_lisap/video/7394107845135928619",
  "submittedVideoUrl": "https://www.tiktok.com/@itsme_lisap/video/7394107845135928619",
  "cid": "7394138825746039582",
  "createTime": 1721582118,
  "createTimeISO": "2024-07-21T17:15:18.000Z",
  "text": "And the fact they put up a go fund me after this…",
  "diggCount": 75,
  "repliesToId": null,
  "replyCommentTotal": 4,
  "uid": "6817839149007520773",
  "uniqueId": "kaylanatalie_",
  "avatarThumbnail": "https://p16-sign-va.tiktokcdn.com/tos-maliva-avt-0068/0b4c8eaeeeb44c81b49fa00f7bd23cfd~c5_100x100.jpg?lk3s=30310797&nonce=15021&refresh_token=4c9489f287a7a85e28fd4ed702c28ad8&x-expires=1737212400&x-signature=F1h3jgOVskhujwUchFS2FbkHjS4%3D&shp=30310797&shcp=-"
},
{
  "videoWebUrl": "https://www.tiktok.com/@itsme_lisap/video/7394107845135928619",
  "submittedVideoUrl": "https://www.tiktok.com/@itsme_lisap/video/7394107845135928619",
  "cid": "7394123751083803438",
  "createTime": 1721578634,
  "createTimeISO": "2024-07-21T16:17:14.000Z",
  "text": "This was no accident. It is heartbreaking that this poor baby was put through this.",
  "diggCount": 91,
  "repliesToId": null,
  "replyCommentTotal": 0,
  "uid": "6918117585184932869",
  "uniqueId": "themoodywife13",
  "avatarThumbnail": "https://p16-sign-va.tiktokcdn.com/tos-maliva-avt-0068/7327824817441406982~c5_100x100.jpg?lk3s=30310797&nonce=29741&refresh_token=6d5c5e62a0dff572ad3fd91f8445996d&x-expires=1737212400&x-signature=i6H64j36nbh3OfPGIQi3bX0DLeo%3D&shp=30310797&shcp=-"
},
{
  "videoWebUrl": "https://www.tiktok.com/@itsme_lisap/video/7394107845135928619",
  "submittedVideoUrl": "https://www.tiktok.com/@itsme_lisap/video/7394107845135928619",
  "cid": "7433337005319291669",
  "createTime": 1730708646,
  "createTimeISO": "2024-11-04T08:24:06.000Z",
  "text": "Aussie peeps. That is almost 49 degrees fyi",
  "diggCount": 1,
  "repliesToId": null,
  "replyCommentTotal": 0,
  "uid": "6913496994884404230",
  "uniqueId": "doofyblanch",
  "avatarThumbnail": "https://p16-sign-sg.tiktokcdn.com/aweme/100x100/tos-alisg-avt-0068/512364fc0825aa13a966e38314101b46.jpg?lk3s=30310797&nonce=58664&refresh_token=6bd1047b883e471cb03bf364f618f82c&x-expires=1737212400&x-signature=qXuB5gNumoM3MjIZyV2f%2FpWynJI%3D&shp=30310797&shcp=-"
},
{
  "videoWebUrl": "https://www.tiktok.com/@itsme_lisap/video/7394107845135928619",
  "submittedVideoUrl": "https://www.tiktok.com/@itsme_lisap/video/7394107845135928619",
  "cid": "7394173729523155755",
  "createTime": 1721590249,
  "createTimeISO": "2024-07-21T19:30:49.000Z",
  "text": "I read an article that said it got up to 120 degrees out there. Who is out with a baby in that, wow.",
  "diggCount": 29,
  "repliesToId": null,
  "replyCommentTotal": 2,
  "uid": "6973032238770439174",
  "uniqueId": "krispypoptartmom",
  "avatarThumbnail": "https://p16-sign-va.tiktokcdn.com/tos-maliva-avt-0068/5c8d1bae5cd4f1c187ec31aeb0c278fa~c5_100x100.jpg?lk3s=30310797&nonce=61547&refresh_token=9b078b17189cfa6805a29f4c3e8abba8&x-expires=1737212400&x-signature=bXp9q9o13P6RLtkdUWiEYsQytgc%3D&shp=30310797&shcp=-"
},
{
  "videoWebUrl": "https://www.tiktok.com/@itsme_lisap/video/7394107845135928619",
  "submittedVideoUrl": "https://www.tiktok.com/@itsme_lisap/video/7394107845135928619",
  "cid": "7394112282232161067",
  "createTime": 1721575964,
  "createTimeISO": "2024-07-21T15:32:44.000Z",
  "text": "I won't even let my 6 month old niece be outside for longer than getting her into a car when it's 85+ here in New England. I am always checking her to make sure she's not overheating.",
  "diggCount": 38,
  "repliesToId": null,
  "replyCommentTotal": 4,
  "uid": "6866945980769731589",
  "uniqueId": "_la__strega_",
  "avatarThumbnail": "https://p16-sign-va.tiktokcdn.com/tos-maliva-avt-0068/16f9ef3366782771e5404d46fe3eab3c~c5_100x100.jpg?lk3s=30310797&nonce=54493&refresh_token=183345205400518db7022580d38461cf&x-expires=1737212400&x-signature=ZKcsoNa2024x1DgbCaA%2FoDeJHR8%3D&shp=30310797&shcp=-"
},
{
  "videoWebUrl": "https://www.tiktok.com/@itsme_lisap/video/7394107845135928619",
  "submittedVideoUrl": "https://www.tiktok.com/@itsme_lisap/video/7394107845135928619",
  "cid": "7394134757628019499",
  "createTime": 1721581193,
  "createTimeISO": "2024-07-21T16:59:53.000Z",
  "text": "Born and raised in Arizona. The heat is no joke. I don’t even let my dogs out except to go potty. It’s ridiculously hot, this was irresponsible and selfish beyond belief!",
  "diggCount": 33,
  "repliesToId": null,
  "replyCommentTotal": 0,
  "uid": "6938619366565872645",
  "uniqueId": "tedstina",
  "avatarThumbnail": "https://p16-sign-va.tiktokcdn.com/tos-maliva-avt-0068/a869aa667bbbf44971f2f8ac31e53dab~c5_100x100.jpg?lk3s=30310797&nonce=87948&refresh_token=a580b52fc8c6a363caf11bceba81d637&x-expires=1737212400&x-signature=vVrQh6mEAdkxgnud%2FRhZ7caVJWo%3D&shp=30310797&shcp=-"
},
{
  "videoWebUrl": "https://www.tiktok.com/@itsme_lisap/video/7394107845135928619",
  "submittedVideoUrl": "https://www.tiktok.com/@itsme_lisap/video/7394107845135928619",
  "cid": "7394139211321312043",
  "createTime": 1721582245,
  "createTimeISO": "2024-07-21T17:17:25.000Z",
  "text": "When my toddler was younger than one I would literally panic about if he was too hot or too cold like in a temperature controlled environment.",
  "diggCount": 17,
  "repliesToId": null,
  "replyCommentTotal": 2,
  "uid": "6813386279914701829",
  "uniqueId": "laurenb1990landon",
  "avatarThumbnail": "https://p16-sign-va.tiktokcdn.com/tos-maliva-avt-0068/7345956927295193131~c5_100x100.jpg?lk3s=30310797&nonce=93848&refresh_token=f9d6a398d8232672c239445bda8b4abe&x-expires=1737212400&x-signature=YOSf%2BX2b%2FGCeXvRxYYV1yg%2FgGC4%3D&shp=30310797&shcp=-"
},
{
  "videoWebUrl": "https://www.tiktok.com/@itsme_lisap/video/7394107845135928619",
  "submittedVideoUrl": "https://www.tiktok.com/@itsme_lisap/video/7394107845135928619",
  "cid": "7394782869086798634",
  "createTime": 1721732175,
  "createTimeISO": "2024-07-23T10:56:15.000Z",
  "text": "I had my first child within 7 days we were in the middle of a hurricane 🌀 spouse was a truck driver. We lost power I realized within 12hours my daughter temp was 100 we got in the car yes in the",
  "diggCount": 1,
  "repliesToId": null,
  "replyCommentTotal": 2,
  "uid": "7167805587739771946",
  "uniqueId": "jessicaxoxoxo88",
  "avatarThumbnail": "https://p16-sign-va.tiktokcdn.com/tos-maliva-avt-0068/ff5fc22549e2e2053472a7d4776afbbf~c5_100x100.jpg?lk3s=30310797&nonce=97011&refresh_token=efa66d81de600479bad1698a757df86b&x-expires=1737212400&x-signature=XplwKMiujLQhZTIMJR3m94MHWok%3D&shp=30310797&shcp=-"
},
{
  "videoWebUrl": "https://www.tiktok.com/@itsme_lisap/video/7394107845135928619",
  "submittedVideoUrl": "https://www.tiktok.com/@itsme_lisap/video/7394107845135928619",
  "cid": "7394162183318242078",
  "createTime": 1721587565,
  "createTimeISO": "2024-07-21T18:46:05.000Z",
  "text": "I wouldn’t take my dog out in that weather…",
  "diggCount": 21,
  "repliesToId": null,
  "replyCommentTotal": 1,
  "uid": "6747895381034402821",
  "uniqueId": "richladyproblems",
  "avatarThumbnail": "https://p16-sign-va.tiktokcdn.com/tos-maliva-avt-0068/ed436925a35421fb272de207d9242286~c5_100x100.jpg?lk3s=30310797&nonce=12061&refresh_token=0461d2feceeadd9e4b15bfb22e133da5&x-expires=1737212400&x-signature=XxUy3uQgSGikThnIBSkO3u339TM%3D&shp=30310797&shcp=-"
},
{
  "videoWebUrl": "https://www.tiktok.com/@itsme_lisap/video/7394107845135928619",
  "submittedVideoUrl": "https://www.tiktok.com/@itsme_lisap/video/7394107845135928619",
  "cid": "7394126770955420446",
  "createTime": 1721579314,
  "createTimeISO": "2024-07-21T16:28:34.000Z",
  "text": "it was 100* last labor day. tried to go to a BBQ at a friend's. brought a fan & UV blocking play thing for my 4 month old. spent most of the time inside in their AC, then left early. it's not hard.",
  "diggCount": 27,
  "repliesToId": null,
  "replyCommentTotal": 0,
  "uid": "6821036216910414853",
  "uniqueId": "k_isob",
  "avatarThumbnail": "https://p16-sign-va.tiktokcdn.com/tos-maliva-avt-0068/7317696978559713326~c5_100x100.jpg?lk3s=30310797&nonce=22694&refresh_token=025d6ddbd0485c05f1a453dd3c46b3e1&x-expires=1737212400&x-signature=7L%2BVXbmyHXdUTWyLVUwq8Z4MPnA%3D&shp=30310797&shcp=-"
},
{
  "videoWebUrl": "https://www.tiktok.com/@itsme_lisap/video/7394107845135928619",
  "submittedVideoUrl": "https://www.tiktok.com/@itsme_lisap/video/7394107845135928619",
  "cid": "7394111981953712939",
  "createTime": 1721575899,
  "createTimeISO": "2024-07-21T15:31:39.000Z",
  "text": "We don’t even go out if it’s hotter than like 85",
  "diggCount": 25,
  "repliesToId": null,
  "replyCommentTotal": 0,
  "uid": "6814482648686674949",
  "uniqueId": "katren922",
  "avatarThumbnail": "https://p16-sign-va.tiktokcdn.com/tos-maliva-avt-0068/a85f087649e8fee258a8d5ae6afe2e96~c5_100x100.jpg?lk3s=30310797&nonce=26145&refresh_token=c3db9377c7934052b9c8b5f01e25d7cb&x-expires=1737212400&x-signature=IT06NM%2FPBPp%2FQ3tt%2F556V%2BS2%2Bbc%3D&shp=30310797&shcp=-"
},
{
  "videoWebUrl": "https://www.tiktok.com/@itsme_lisap/video/7394107845135928619",
  "submittedVideoUrl": "https://www.tiktok.com/@itsme_lisap/video/7394107845135928619",
  "cid": "7394115857087791914",
  "createTime": 1721576799,
  "createTimeISO": "2024-07-21T15:46:39.000Z",
  "text": "I have had 4 summer babies in a hot environment and this just blows my mind.",
  "diggCount": 17,
  "repliesToId": null,
  "replyCommentTotal": 0,
  "uid": "128700055716327424",
  "uniqueId": "valley_grown",
  "avatarThumbnail": "https://p16-sign-va.tiktokcdn.com/tos-maliva-avt-0068/6c863c1f8f12906c8ac4aff73b18d8d4~c5_100x100.jpg?lk3s=30310797&nonce=97760&refresh_token=7218f6e7cb4f8115fe4d448dbed2a0ab&x-expires=1737212400&x-signature=G6nrI6VNrOdKaN2RD921ppybcvs%3D&shp=30310797&shcp=-"
},
{
  "videoWebUrl": "https://www.tiktok.com/@itsme_lisap/video/7394107845135928619",
  "submittedVideoUrl": "https://www.tiktok.com/@itsme_lisap/video/7394107845135928619",
  "cid": "7394178113440269087",
  "createTime": 1721591277,
  "createTimeISO": "2024-07-21T19:47:57.000Z",
  "text": "It's been so hot here in Arizona that I won't even take my 19 yr old special needs son to the lake because he can't communicate if he's not doing good! I've gotten a sitter for him!",
  "diggCount": 10,
  "repliesToId": null,
  "replyCommentTotal": 0,
  "uid": "6719971803488404486",
  "uniqueId": "shannonbrowning0",
  "avatarThumbnail": "https://p16-sign-va.tiktokcdn.com/tos-maliva-avt-0068/fd550e34d042aefe785fbfc7c9cd60f3~c5_100x100.jpg?lk3s=30310797&nonce=80340&refresh_token=330d831f7c1bf8a5c42c77201af118a0&x-expires=1737212400&x-signature=aKH%2BM4TCcqblmMbGgU74yrlzprw%3D&shp=30310797&shcp=-"
},
{
  "videoWebUrl": "https://www.tiktok.com/@itsme_lisap/video/7394107845135928619",
  "submittedVideoUrl": "https://www.tiktok.com/@itsme_lisap/video/7394107845135928619",
  "cid": "7394109961859547935",
  "createTime": 1721575419,
  "createTimeISO": "2024-07-21T15:23:39.000Z",
  "text": "100% This, all this. Thank you for stating this.",
  "diggCount": 9,
  "repliesToId": null,
  "replyCommentTotal": 0,
  "uid": "6880344282591577094",
  "uniqueId": "lanacan",
  "avatarThumbnail": "https://p16-sign-va.tiktokcdn.com/tos-maliva-avt-0068/7352871920318021674~c5_100x100.jpg?lk3s=30310797&nonce=33764&refresh_token=0a722e049d8c9cf359a48633faa28ac6&x-expires=1737212400&x-signature=2460qqzhNuw%2BBBIDenvYWqqCYLk%3D&shp=30310797&shcp=-"
},
{
  "videoWebUrl": "https://www.tiktok.com/@itsme_lisap/video/7394107845135928619",
  "submittedVideoUrl": "https://www.tiktok.com/@itsme_lisap/video/7394107845135928619",
  "cid": "7397607598666597150",
  "createTime": 1722389741,
  "createTimeISO": "2024-07-31T01:35:41.000Z",
  "text": "Truth when are they going to be arrested?’",
  "diggCount": 4,
  "repliesToId": null,
  "replyCommentTotal": 0,
  "uid": "7124878354244043819",
  "uniqueId": "user2085331205572",
  "avatarThumbnail": "https://p16-sign-va.tiktokcdn.com/musically-maliva-obj/1594805258216454~c5_100x100.jpg?lk3s=30310797&nonce=23331&refresh_token=c082803c74b8c0f6450cc243447af672&x-expires=1737212400&x-signature=sj5DVp7Hy7TTQGluyFHHs7MACmM%3D&shp=30310797&shcp=-"
},
{
  "videoWebUrl": "https://www.tiktok.com/@itsme_lisap/video/7394107845135928619",
  "submittedVideoUrl": "https://www.tiktok.com/@itsme_lisap/video/7394107845135928619",
  "cid": "7394206766105936686",
  "createTime": 1721597947,
  "createTimeISO": "2024-07-21T21:39:07.000Z",
  "text": "I have an 8 month old and I don’t even like bringing her out in 80° heat. 😢",
  "diggCount": 7,
  "repliesToId": null,
  "replyCommentTotal": 0,
  "uid": "6781874285428605957",
  "uniqueId": "heythereitsbecca__",
  "avatarThumbnail": "https://p16-sign-va.tiktokcdn.com/tos-maliva-avt-0068/f110b57ec7e610ceb03cd442e4e24c09~c5_100x100.jpg?lk3s=30310797&nonce=42476&refresh_token=38ca4b64c20e90064b5c8626ce6e371a&x-expires=1737212400&x-signature=ke5WSpo1PWg0iHfCoOmYG6YhDlo%3D&shp=30310797&shcp=-"
},
{
  "videoWebUrl": "https://www.tiktok.com/@itsme_lisap/video/7394107845135928619",
  "submittedVideoUrl": "https://www.tiktok.com/@itsme_lisap/video/7394107845135928619",
  "cid": "7401389295503033118",
  "createTime": 1723270249,
  "createTimeISO": "2024-08-10T06:10:49.000Z",
  "text": "Are there any updates. This bothers me so much. Police protecting thier😏 own",
  "diggCount": 2,
  "repliesToId": null,
  "replyCommentTotal": 0,
  "uid": "6744132974260257798",
  "uniqueId": "jenleetee",
  "avatarThumbnail": "https://p16-sign-va.tiktokcdn.com/tos-maliva-avt-0068/7324323914989027333~c5_100x100.jpg?lk3s=30310797&nonce=79662&refresh_token=43d8791a17dfdc22d960ddd5d409272a&x-expires=1737212400&x-signature=Y51oNV8Y7o50JjCrecz60w821pw%3D&shp=30310797&shcp=-"
},
{
  "videoWebUrl": "https://www.tiktok.com/@itsme_lisap/video/7394107845135928619",
  "submittedVideoUrl": "https://www.tiktok.com/@itsme_lisap/video/7394107845135928619",
  "cid": "7394238938238190367",
  "createTime": 1721605432,
  "createTimeISO": "2024-07-21T23:43:52.000Z",
  "text": "I went to shasta that same week. I LEFT MY KIDS HOME WITH THE GRANDPARENTS BECAUSE I CHECKED THE WEATHER AND IT WAS GOING TO BE 115 DEGREES. THIS BLOWS MY MIND",
  "diggCount": 3,
  "repliesToId": null,
  "replyCommentTotal": 0,
  "uid": "6773864623097119749",
  "uniqueId": "emilyymortensen",
  "avatarThumbnail": "https://p16-sign-va.tiktokcdn.com/tos-maliva-avt-0068/2df94a5634e292b55be4394d6dffa22f~c5_100x100.jpg?lk3s=30310797&nonce=71602&refresh_token=5de00d8cd815e00b1989466c3f0700c1&x-expires=1737212400&x-signature=I93QPf6RDPkMQwgFlli88ARi2BU%3D&shp=30310797&shcp=-"
},
{
  "videoWebUrl": "https://www.tiktok.com/@itsme_lisap/video/7394107845135928619",
  "submittedVideoUrl": "https://www.tiktok.com/@itsme_lisap/video/7394107845135928619",
  "cid": "7396220837978686238",
  "createTime": 1722066912,
  "createTimeISO": "2024-07-27T07:55:12.000Z",
  "text": "I can’t even do 90% weather…",
  "diggCount": 2,
  "repliesToId": null,
  "replyCommentTotal": 0,
  "uid": "7116324040721515563",
  "uniqueId": "defnot_serenity7",
  "avatarThumbnail": "https://p16-sign-va.tiktokcdn.com/tos-maliva-avt-0068/2ab4c6c877e0d95394f6e652c3042b8b~c5_100x100.jpg?lk3s=30310797&nonce=38430&refresh_token=fd083f310cc855050ebf46b19a749e44&x-expires=1737212400&x-signature=2GRu0LjZO4wukXDJ57ScpPIHcHw%3D&shp=30310797&shcp=-"
},
{
  "videoWebUrl": "https://www.tiktok.com/@itsme_lisap/video/7394107845135928619",
  "submittedVideoUrl": "https://www.tiktok.com/@itsme_lisap/video/7394107845135928619",
  "cid": "7419142785138377503",
  "createTime": 1727403800,
  "createTimeISO": "2024-09-27T02:23:20.000Z",
  "text": "Rip to that sweet child. This is so heartbreaking.",
  "diggCount": 1,
  "repliesToId": null,
  "replyCommentTotal": 0,
  "uid": "6854894714215777286",
  "uniqueId": "rd1223",
  "avatarThumbnail": "https://p16-sign-va.tiktokcdn.com/tos-maliva-avt-0068/0ec6715552c4d1fe5b451db592f92c88~c5_100x100.jpg?lk3s=30310797&nonce=93444&refresh_token=8531b358772dff3d3c7ab47ba74910c3&x-expires=1737212400&x-signature=8hXWI%2FbdbhHWb1vuQCejLorCIPU%3D&shp=30310797&shcp=-"
},
{
  "videoWebUrl": "https://www.tiktok.com/@itsme_lisap/video/7394107845135928619",
  "submittedVideoUrl": "https://www.tiktok.com/@itsme_lisap/video/7394107845135928619",
  "cid": "7394153554003362566",
  "createTime": 1721585549,
  "createTimeISO": "2024-07-21T18:12:29.000Z",
  "text": "my dogs are only out to do their business for petes sake\n😔",
  "diggCount": 3,
  "repliesToId": null,
  "replyCommentTotal": 0,
  "uid": "7001287137140622341",
  "uniqueId": "on_can_momma",
  "avatarThumbnail": "https://p16-sign-va.tiktokcdn.com/tos-maliva-avt-0068/2d8de6b352a8cc8b46eb58c346913c0b~c5_100x100.jpg?lk3s=30310797&nonce=69618&refresh_token=81881d044d43217d9a9119ced106df4f&x-expires=1737212400&x-signature=u9DkbEdt5KMRVzsfS4lnbACuV8s%3D&shp=30310797&shcp=-"
},
{
  "videoWebUrl": "https://www.tiktok.com/@itsme_lisap/video/7394107845135928619",
  "submittedVideoUrl": "https://www.tiktok.com/@itsme_lisap/video/7394107845135928619",
  "cid": "7399346190271234846",
  "createTime": 1722794539,
  "createTimeISO": "2024-08-04T18:02:19.000Z",
  "text": "I lived in Lake Havasu. You don’t go on the lake in extreme heat!",
  "diggCount": 1,
  "repliesToId": null,
  "replyCommentTotal": 0,
  "uid": "6646065526404464645",
  "uniqueId": "weimeranerfun",
  "avatarThumbnail": "https://p16-sign-va.tiktokcdn.com/tos-maliva-avt-0068/4ec19eb0b370af115812d82883a67d15~c5_100x100.jpg?lk3s=30310797&nonce=76807&refresh_token=f1738c64d73333a1bbb8da4bc3f6f776&x-expires=1737212400&x-signature=xZWHuHvLhe3hLZRrn6GK2gGKu%2B8%3D&shp=30310797&shcp=-"
},
{
  "videoWebUrl": "https://www.tiktok.com/@itsme_lisap/video/7394107845135928619",
  "submittedVideoUrl": "https://www.tiktok.com/@itsme_lisap/video/7394107845135928619",
  "cid": "7394167522456634142",
  "createTime": 1721588800,
  "createTimeISO": "2024-07-21T19:06:40.000Z",
  "text": "we are not out side people, no human is- this is awful",
  "diggCount": 1,
  "repliesToId": null,
  "replyCommentTotal": 0,
  "uid": "6627111152466755590",
  "uniqueId": "0192stephanie",
  "avatarThumbnail": "https://p16-sign-va.tiktokcdn.com/tos-maliva-avt-0068/7328744982491103237~c5_100x100.jpg?lk3s=30310797&nonce=9635&refresh_token=8b00f40467841ff86c770385cd3d6824&x-expires=1737212400&x-signature=DZDnv824o%2Bjc6RrthuLOqM0KO%2B4%3D&shp=30310797&shcp=-"
},
{
  "videoWebUrl": "https://www.tiktok.com/@itsme_lisap/video/7394107845135928619",
  "submittedVideoUrl": "https://www.tiktok.com/@itsme_lisap/video/7394107845135928619",
  "cid": "7399654435146826538",
  "createTime": 1722866416,
  "createTimeISO": "2024-08-05T14:00:16.000Z",
  "text": "Infuriating",
  "diggCount": 0,
  "repliesToId": null,
  "replyCommentTotal": 0,
  "uid": "6757859538530452486",
  "uniqueId": "alissamg43",
  "avatarThumbnail": "https://p16-sign-va.tiktokcdn.com/tos-maliva-avt-0068/237be04bc25ce16870b7488571e61529~c5_100x100.jpg?lk3s=30310797&nonce=74742&refresh_token=ab1e6635495959dcab141e4abc9e3bf5&x-expires=1737212400&x-signature=U43TwRuxPwmmBPUiDEQ98nRN3W8%3D&shp=30310797&shcp=-"
},
{
  "videoWebUrl": "https://www.tiktok.com/@itsme_lisap/video/7394107845135928619",
  "submittedVideoUrl": "https://www.tiktok.com/@itsme_lisap/video/7394107845135928619",
  "cid": "7400391772260303647",
  "createTime": 1723037990,
  "createTimeISO": "2024-08-07T13:39:50.000Z",
  "text": "I live in Austin TX and I think the highest I've felt is 108°. it's really hard to describe just how 🔥🔥🔥 that is. it's difficult to be outside for any amount of time. they knew. they knew",
  "diggCount": 0,
  "repliesToId": null,
  "replyCommentTotal": 0,
  "uid": "6983145447260111877",
  "uniqueId": "annamariefrancois",
  "avatarThumbnail": "https://p16-sign-va.tiktokcdn.com/tos-maliva-avt-0068/8aac7785c4fbd8ecd8f0b75e9333371c~c5_100x100.jpg?lk3s=30310797&nonce=47638&refresh_token=8595ca92061f479740e02b5373179abd&x-expires=1737212400&x-signature=KWlTeF6Z8DWE42j23iXOtRHRkjU%3D&shp=30310797&shcp=-"
},
{
  "videoWebUrl": "https://www.tiktok.com/@itsme_lisap/video/7394107845135928619",
  "submittedVideoUrl": "https://www.tiktok.com/@itsme_lisap/video/7394107845135928619",
  "cid": "7402454755555558186",
  "createTime": 1723518354,
  "createTimeISO": "2024-08-13T03:05:54.000Z",
  "text": "WHY HAVEN'T THEY BEEN CHARGED?!?!",
  "diggCount": 0,
  "repliesToId": null,
  "replyCommentTotal": 0,
  "uid": "6761626630324028421",
  "uniqueId": "katiemassage7",
  "avatarThumbnail": "https://p16-sign-va.tiktokcdn.com/tos-maliva-avt-0068/d3217d33d7eb92c0e4af0c65436cfe0e~c5_100x100.jpg?lk3s=30310797&nonce=34730&refresh_token=6f687dc1c30447f9639b4deebd8015b4&x-expires=1737212400&x-signature=sJlSZ4UGD1wlgxcgWm0AKwXofow%3D&shp=30310797&shcp=-"
},
{
  "videoWebUrl": "https://www.tiktok.com/@itsme_lisap/video/7394107845135928619",
  "submittedVideoUrl": "https://www.tiktok.com/@itsme_lisap/video/7394107845135928619",
  "cid": "7396800786581947166",
  "createTime": 1722201909,
  "createTimeISO": "2024-07-28T21:25:09.000Z",
  "text": "It’s been so long nothing new I keep checking",
  "diggCount": 0,
  "repliesToId": null,
  "replyCommentTotal": 0,
  "uid": "7114717455227864110",
  "uniqueId": "jacklyn6028",
  "avatarThumbnail": "https://p16-sign-va.tiktokcdn.com/tos-maliva-avt-0068/d7c4e069995fe0f9adc589e9d452a45c~c5_100x100.jpg?lk3s=30310797&nonce=35752&refresh_token=3641efdbf65a2c2ebcda83e28946646c&x-expires=1737212400&x-signature=RZZu5acWaaAVQ5d8b2VADydfXZ4%3D&shp=30310797&shcp=-"
},
{
  "videoWebUrl": "https://www.tiktok.com/@itsme_lisap/video/7394107845135928619",
  "submittedVideoUrl": "https://www.tiktok.com/@itsme_lisap/video/7394107845135928619",
  "cid": "7396378734787838751",
  "createTime": 1722103641,
  "createTimeISO": "2024-07-27T18:07:21.000Z",
  "text": "Exactly and this was not their first child they have a toddler. My husband only had every other weekend when the kids were little so unless it was a family party get together we didn’t go. We had plenty of other times to do childless activities children safety always.",
  "diggCount": 0,
  "repliesToId": null,
  "replyCommentTotal": 0,
  "uid": "6899568567336633350",
  "uniqueId": "capecodstepmom",
  "avatarThumbnail": "https://p16-sign-va.tiktokcdn.com/tos-maliva-avt-0068/7330748646398525445~c5_100x100.jpg?lk3s=30310797&nonce=46356&refresh_token=c4e07633766a8e5c4521e69ff3868fb6&x-expires=1737212400&x-signature=gLNjdGUiPP36uSgQU%2BEfe909Xm0%3D&shp=30310797&shcp=-"
},
{
  "videoWebUrl": "https://www.tiktok.com/@itsme_lisap/video/7394107845135928619",
  "submittedVideoUrl": "https://www.tiktok.com/@itsme_lisap/video/7394107845135928619",
  "cid": "7394294224596386603",
  "createTime": 1721618312,
  "createTimeISO": "2024-07-22T03:18:32.000Z",
  "text": "Oh my. This is so sad.",
  "diggCount": 0,
  "repliesToId": null,
  "replyCommentTotal": 0,
  "uid": "207062023199842304",
  "uniqueId": "kittypantsmcmewey",
  "avatarThumbnail": "https://p16-sign-va.tiktokcdn.com/musically-maliva-obj/1594805258216454~c5_100x100.jpg?lk3s=30310797&nonce=70122&refresh_token=0aef9718d0df6e6836fab2bdbe27c186&x-expires=1737212400&x-signature=sj5DVp7Hy7TTQGluyFHHs7MACmM%3D&shp=30310797&shcp=-"
},
{
  "videoWebUrl": "https://www.tiktok.com/@itsme_lisap/video/7394107845135928619",
  "submittedVideoUrl": "https://www.tiktok.com/@itsme_lisap/video/7394107845135928619",
  "cid": "7394519878923354910",
  "createTime": 1721670845,
  "createTimeISO": "2024-07-22T17:54:05.000Z",
  "text": "I don’t even let my teenager outside if it’s that hot out. The risks just aren’t worth it.",
  "diggCount": 0,
  "repliesToId": null,
  "replyCommentTotal": 0,
  "uid": "6805207951297905670",
  "uniqueId": "_arianadanielle",
  "avatarThumbnail": "https://p16-sign-va.tiktokcdn.com/tos-maliva-avt-0068/1b3c00c00e6eebe1f28d2a3ae4c4c80c~c5_100x100.jpg?lk3s=30310797&nonce=52914&refresh_token=ae9b19e194e1c6f1e3dddf7ad2f666d8&x-expires=1737212400&x-signature=LQ9SQqx58C25UH%2FPAlIA2hrFIoA%3D&shp=30310797&shcp=-"
},
{
  "videoWebUrl": "https://www.tiktok.com/@itsme_lisap/video/7394107845135928619",
  "submittedVideoUrl": "https://www.tiktok.com/@itsme_lisap/video/7394107845135928619",
  "cid": "7394823559387906858",
  "createTime": 1721741565,
  "createTimeISO": "2024-07-23T13:32:45.000Z",
  "text": "That’s even more disgusting. You killed your own child to go have fun on a lake and then you wanna ask us for money after you killed your own child fuck you go to jail.!!",
  "diggCount": 3,
  "repliesToId": "7394138825746039582",
  "replyCommentTotal": null,
  "uid": "6860822999395599366",
  "uniqueId": "mariahleigh85",
  "avatarThumbnail": "https://p16-pu-sign-useast8.tiktokcdn-us.com/tos-useast8-avt-0068-tx2/8435da06290bc935fef6108414b94c42~c5_100x100.jpg?lk3s=30310797&nonce=26436&refresh_token=a7a6462242d55ab4122c27c46fb15eb9&x-expires=1737212400&x-signature=%2BeWGovo%2B1nVdn5aI8gram%2BM%2BIcs%3D&shp=30310797&shcp=-"
},
{
  "videoWebUrl": "https://www.tiktok.com/@itsme_lisap/video/7394107845135928619",
  "submittedVideoUrl": "https://www.tiktok.com/@itsme_lisap/video/7394107845135928619",
  "cid": "7395313863061062431",
  "createTime": 1721855698,
  "createTimeISO": "2024-07-24T21:14:58.000Z",
  "text": "Twice! Took it down and put it back up again to finish collecting their original amount. Gross.",
  "diggCount": 6,
  "repliesToId": "7394138825746039582",
  "replyCommentTotal": null,
  "uid": "6749964192838779909",
  "uniqueId": "kdiatl",
  "avatarThumbnail": "https://p16-pu-sign-useast8.tiktokcdn-us.com/tos-useast5-avt-0068-tx/6dff6e75c4a050e55913d8b7ab9ac9bb~c5_100x100.jpg?lk3s=30310797&nonce=81734&refresh_token=9ea79b856a8e5d64d46c11a05235eb1a&x-expires=1737212400&x-signature=Xhdiud3HqEGv03gLUlUAO%2FdYLTM%3D&shp=30310797&shcp=-"
},
{
  "videoWebUrl": "https://www.tiktok.com/@itsme_lisap/video/7394107845135928619",
  "submittedVideoUrl": "https://www.tiktok.com/@itsme_lisap/video/7394107845135928619",
  "cid": "7398744969769567006",
  "createTime": 1722654558,
  "createTimeISO": "2024-08-03T03:09:18.000Z",
  "text": "it's gross that they got that money in the first place.",
  "diggCount": 3,
  "repliesToId": "7394138825746039582",
  "replyCommentTotal": null,
  "uid": "75993272761917440",
  "uniqueId": "krazyk00luv",
  "avatarThumbnail": "https://p16-pu-sign-useast8.tiktokcdn-us.com/tos-useast5-avt-0068-tx/7351363991874043946~c5_100x100.jpg?lk3s=30310797&nonce=83408&refresh_token=d7106b0ff07937e49d5ca9216179dea6&x-expires=1737212400&x-signature=bLIi%2FCJoqfG41GLraHoSLEYdxh8%3D&shp=30310797&shcp=-"
},
{
  "videoWebUrl": "https://www.tiktok.com/@itsme_lisap/video/7394107845135928619",
  "submittedVideoUrl": "https://www.tiktok.com/@itsme_lisap/video/7394107845135928619",
  "cid": "7398863364740465439",
  "createTime": 1722682129,
  "createTimeISO": "2024-08-03T10:48:49.000Z",
  "text": "Absolutely!!!",
  "diggCount": 2,
  "repliesToId": "7394138825746039582",
  "replyCommentTotal": null,
  "uid": "6749964192838779909",
  "uniqueId": "kdiatl",
  "avatarThumbnail": "https://p16-pu-sign-useast8.tiktokcdn-us.com/tos-useast5-avt-0068-tx/6dff6e75c4a050e55913d8b7ab9ac9bb~c5_100x100.jpg?lk3s=30310797&nonce=81734&refresh_token=9ea79b856a8e5d64d46c11a05235eb1a&x-expires=1737212400&x-signature=Xhdiud3HqEGv03gLUlUAO%2FdYLTM%3D&shp=30310797&shcp=-"
},
{
  "videoWebUrl": "https://www.tiktok.com/@itsme_lisap/video/7394107845135928619",
  "submittedVideoUrl": "https://www.tiktok.com/@itsme_lisap/video/7394107845135928619",
  "cid": "7398207015145161503",
  "createTime": 1722529305,
  "createTimeISO": "2024-08-01T16:21:45.000Z",
  "text": "it get up to 130 in Havasu. typically hotter than Death Valley, if that puts it in perspective. 😓",
  "diggCount": 0,
  "repliesToId": "7394173729523155755",
  "replyCommentTotal": null,
  "uid": "6981946457713263622",
  "uniqueId": "casslovering",
  "avatarThumbnail": "https://p16-sign.tiktokcdn-us.com/tos-useast5-avt-0068-tx/940835147e1c1bfd2bc456f1c2e18fa7~c5_100x100.jpg?lk3s=30310797&nonce=60553&refresh_token=3ac02a6c5d8c24cdb23b3a536ef57b18&x-expires=1737212400&x-signature=QybdZM%2BQOt0XNZWRHclorPgiStQ%3D&shp=30310797&shcp=-"
},
{
  "videoWebUrl": "https://www.tiktok.com/@itsme_lisap/video/7394107845135928619",
  "submittedVideoUrl": "https://www.tiktok.com/@itsme_lisap/video/7394107845135928619",
  "cid": "7394273181152805662",
  "createTime": 1721613402,
  "createTimeISO": "2024-07-22T01:56:42.000Z",
  "text": "Temp thermometer showed 125 degrees",
  "diggCount": 2,
  "repliesToId": "7394173729523155755",
  "replyCommentTotal": null,
  "uid": "6971276511149573126",
  "uniqueId": "pamkenperez",
  "avatarThumbnail": "https://p19-pu-sign-useast8.tiktokcdn-us.com/tos-useast8-avt-0068-tx2/4ca52e9deeaac61bfe7c833e08518778~c5_100x100.jpg?lk3s=30310797&nonce=12582&refresh_token=fd7eaacb8e7fc7e27b0fbec4af0fdfcb&x-expires=1737212400&x-signature=tGifFjljEWpIfsJrxNZMGYiGKTU%3D&shp=30310797&shcp=-"
},
{
  "videoWebUrl": "https://www.tiktok.com/@itsme_lisap/video/7394107845135928619",
  "submittedVideoUrl": "https://www.tiktok.com/@itsme_lisap/video/7394107845135928619",
  "cid": "7394114512687760170",
  "createTime": 1721576480,
  "createTimeISO": "2024-07-21T15:41:20.000Z",
  "text": "Not only expected to be OK and to be forgiven, but then to have a go fund me for 50,000 fucking dollars!! shame on them they should have any other children in the home taken,pets taken!",
  "diggCount": 6,
  "repliesToId": "7394112282232161067",
  "replyCommentTotal": null,
  "uid": "6860822999395599366",
  "uniqueId": "mariahleigh85",
  "avatarThumbnail": "https://p19-pu-sign-useast8.tiktokcdn-us.com/tos-useast8-avt-0068-tx2/8435da06290bc935fef6108414b94c42~c5_100x100.jpg?lk3s=30310797&nonce=15828&refresh_token=2ab7b73bd5b5d69e0bafa5f90a862f67&x-expires=1737212400&x-signature=095DCOT8RmF6ci2EeUFYYC8LcuE%3D&shp=30310797&shcp=-"
},
{
  "videoWebUrl": "https://www.tiktok.com/@itsme_lisap/video/7394107845135928619",
  "submittedVideoUrl": "https://www.tiktok.com/@itsme_lisap/video/7394107845135928619",
  "cid": "7394112835481174826",
  "createTime": 1721576084,
  "createTimeISO": "2024-07-21T15:34:44.000Z",
  "text": "my entire family is so protective of her. I do not understand how people think something like that is ok, and then expect to be forgiven when it's their fault.",
  "diggCount": 2,
  "repliesToId": "7394112282232161067",
  "replyCommentTotal": null,
  "uid": "6866945980769731589",
  "uniqueId": "_la__strega_",
  "avatarThumbnail": "https://p19-pu-sign-useast8.tiktokcdn-us.com/tos-useast5-avt-0068-tx/16f9ef3366782771e5404d46fe3eab3c~c5_100x100.jpg?lk3s=30310797&nonce=51495&refresh_token=bfdb1d58b1a59d902461238f4fbb56ab&x-expires=1737212400&x-signature=JKAVuqvzMI%2FdSn0TTGMIF7F40%2BY%3D&shp=30310797&shcp=-"
},
{
  "videoWebUrl": "https://www.tiktok.com/@itsme_lisap/video/7394107845135928619",
  "submittedVideoUrl": "https://www.tiktok.com/@itsme_lisap/video/7394107845135928619",
  "cid": "7394114679801201450",
  "createTime": 1721576526,
  "createTimeISO": "2024-07-21T15:42:06.000Z",
  "text": "How can you be so selfish and neglectful to your baby like it’s just disgusting!!",
  "diggCount": 1,
  "repliesToId": "7394112282232161067",
  "replyCommentTotal": null,
  "uid": "6860822999395599366",
  "uniqueId": "mariahleigh85",
  "avatarThumbnail": "https://p19-pu-sign-useast8.tiktokcdn-us.com/tos-useast8-avt-0068-tx2/8435da06290bc935fef6108414b94c42~c5_100x100.jpg?lk3s=30310797&nonce=15828&refresh_token=2ab7b73bd5b5d69e0bafa5f90a862f67&x-expires=1737212400&x-signature=095DCOT8RmF6ci2EeUFYYC8LcuE%3D&shp=30310797&shcp=-"
},
{
  "videoWebUrl": "https://www.tiktok.com/@itsme_lisap/video/7394107845135928619",
  "submittedVideoUrl": "https://www.tiktok.com/@itsme_lisap/video/7394107845135928619",
  "cid": "7394113595587396398",
  "createTime": 1721576280,
  "createTimeISO": "2024-07-21T15:38:00.000Z",
  "text": "Same with us in Texas. I have a 5 yo with heart issues. She goes from the house to the cooled car. Parks are only in the early morning.",
  "diggCount": 1,
  "repliesToId": "7394112282232161067",
  "replyCommentTotal": null,
  "uid": "6825336663837901829",
  "uniqueId": "annxbt014",
  "avatarThumbnail": "https://p19-pu-sign-useast8.tiktokcdn-us.com/tos-useast5-avt-0068-tx/2ec891bbdb7bef3133b19aa85492e30a~c5_100x100.jpg?lk3s=30310797&nonce=62549&refresh_token=9dca4042b48774905ea157f2aa0f89b7&x-expires=1737212400&x-signature=N%2FCBCRqSn3OBzDviQIH88hmLMLE%3D&shp=30310797&shcp=-"
},
{
  "videoWebUrl": "https://www.tiktok.com/@itsme_lisap/video/7394107845135928619",
  "submittedVideoUrl": "https://www.tiktok.com/@itsme_lisap/video/7394107845135928619",
  "cid": "7394139518234051370",
  "createTime": 1721582286,
  "createTimeISO": "2024-07-21T17:18:06.000Z",
  "text": "And I still do but I’m not as paranoid when he’s taking a nap in our air conditioned house.",
  "diggCount": 2,
  "repliesToId": "7394139211321312043",
  "replyCommentTotal": null,
  "uid": "6813386279914701829",
  "uniqueId": "laurenb1990landon",
  "avatarThumbnail": "https://p19-sign.tiktokcdn-us.com/tos-useast5-avt-0068-tx/7345956927295193131~c5_100x100.jpg?lk3s=30310797&nonce=99216&refresh_token=aeeccb53cd5defa731b8c4ba823a7341&x-expires=1737212400&x-signature=kKNRBcclsQMwlQqOhvnPUmSGXRk%3D&shp=30310797&shcp=-"
},
{
  "videoWebUrl": "https://www.tiktok.com/@itsme_lisap/video/7394107845135928619",
  "submittedVideoUrl": "https://www.tiktok.com/@itsme_lisap/video/7394107845135928619",
  "cid": "7394273514197697310",
  "createTime": 1721613485,
  "createTimeISO": "2024-07-22T01:58:05.000Z",
  "text": "This couple was partying… their child was not a priority. Their needs and wants were.",
  "diggCount": 0,
  "repliesToId": "7394139211321312043",
  "replyCommentTotal": null,
  "uid": "6971276511149573126",
  "uniqueId": "pamkenperez",
  "avatarThumbnail": "https://p19-pu-sign-useast8.tiktokcdn-us.com/tos-useast8-avt-0068-tx2/4ca52e9deeaac61bfe7c833e08518778~c5_100x100.jpg?lk3s=30310797&nonce=4110&refresh_token=ef0d35edb6b4a924688da45c0d72a151&x-expires=1737212400&x-signature=tGifFjljEWpIfsJrxNZMGYiGKTU%3D&shp=30310797&shcp=-"
},
{
  "videoWebUrl": "https://www.tiktok.com/@itsme_lisap/video/7394107845135928619",
  "submittedVideoUrl": "https://www.tiktok.com/@itsme_lisap/video/7394107845135928619",
  "cid": "7394783714666300206",
  "createTime": 1721732324,
  "createTimeISO": "2024-07-23T10:58:44.000Z",
  "text": "- This is no accident -",
  "diggCount": 1,
  "repliesToId": "7394782869086798634",
  "replyCommentTotal": null,
  "uid": "7167805587739771946",
  "uniqueId": "jessicaxoxoxo88",
  "avatarThumbnail": "https://p16-sign-va.tiktokcdn.com/tos-maliva-avt-0068/ff5fc22549e2e2053472a7d4776afbbf~c5_100x100.jpg?lk3s=30310797&nonce=2986&refresh_token=3c6e8c98afa8ad54ec27818ebfb50656&x-expires=1737212400&x-signature=XplwKMiujLQhZTIMJR3m94MHWok%3D&shp=30310797&shcp=-"
},
{
  "videoWebUrl": "https://www.tiktok.com/@itsme_lisap/video/7394107845135928619",
  "submittedVideoUrl": "https://www.tiktok.com/@itsme_lisap/video/7394107845135928619",
  "cid": "7394783383710712618",
  "createTime": 1721732255,
  "createTimeISO": "2024-07-23T10:57:35.000Z",
  "text": "Middle of a hurricane and drove to Indiana to be with my family. Also within 24hrs she was in a pediatricians office… I was told I made the right choice and it was due to the heat in the house.",
  "diggCount": 0,
  "repliesToId": "7394782869086798634",
  "replyCommentTotal": null,
  "uid": "7167805587739771946",
  "uniqueId": "jessicaxoxoxo88",
  "avatarThumbnail": "https://p16-sign-va.tiktokcdn.com/tos-maliva-avt-0068/ff5fc22549e2e2053472a7d4776afbbf~c5_100x100.jpg?lk3s=30310797&nonce=2986&refresh_token=3c6e8c98afa8ad54ec27818ebfb50656&x-expires=1737212400&x-signature=XplwKMiujLQhZTIMJR3m94MHWok%3D&shp=30310797&shcp=-"
},
{
  "videoWebUrl": "https://www.tiktok.com/@itsme_lisap/video/7394107845135928619",
  "submittedVideoUrl": "https://www.tiktok.com/@itsme_lisap/video/7394107845135928619",
  "cid": "7394207610706674478",
  "createTime": 1721598146,
  "createTimeISO": "2024-07-21T21:42:26.000Z",
  "text": "I wouldn't either! I don't have kids but there's no way I would think it's a good idea to take my dog out in hot weather on a boat where there's literally nowhere for them to go to escape the heat.",
  "diggCount": 1,
  "repliesToId": "7394162183318242078",
  "replyCommentTotal": null,
  "uid": "7001668497495573509",
  "uniqueId": "stephanieblasyak80",
  "avatarThumbnail": "https://p16-pu-sign-useast8.tiktokcdn-us.com/tos-useast5-avt-0068-tx/7322008779040489515~c5_100x100.jpg?lk3s=30310797&nonce=73234&refresh_token=75337e38889064da37b4f078f39dd770&x-expires=1737212400&x-signature=7mB6IH%2BkPlF3Ap34bsMYUgSXVG0%3D&shp=30310797&shcp=-"
},
{
  "videoWebUrl": "https://www.tiktok.com/@itsme_lisap/video/7394107845135928619",
  "submittedVideoUrl": "https://www.tiktok.com/@itsme_lisap/video/7394107845135928619",
  "cid": "7394113904408101663",
  "createTime": 1721576323,
  "createTimeISO": "2024-07-21T15:38:43.000Z",
  "text": "💔💔💔💔",
  "diggCount": 5,
  "repliesToId": null,
  "replyCommentTotal": 0,
  "uid": "6800202857804170245",
  "uniqueId": "camirenee11",
  "avatarThumbnail": "https://p16-sign-va.tiktokcdn.com/tos-maliva-avt-0068/7322831520468172806~c5_100x100.jpg?lk3s=30310797&nonce=83687&refresh_token=1778c46bcf95a7713cd5dd9be1358728&x-expires=1737212400&x-signature=qpNpTSmNTj%2BA8HYDwiYlKQA9p6U%3D&shp=30310797&shcp=-"
},
{
  "videoWebUrl": "https://www.tiktok.com/@itsme_lisap/video/7394107845135928619",
  "submittedVideoUrl": "https://www.tiktok.com/@itsme_lisap/video/7394107845135928619",
  "cid": "7394142309622842154",
  "createTime": 1721582940,
  "createTimeISO": "2024-07-21T17:29:00.000Z",
  "text": "👏🏻👏🏻👏🏻",
  "diggCount": 4,
  "repliesToId": null,
  "replyCommentTotal": 0,
  "uid": "6772696840384300037",
  "uniqueId": "angela.spears",
  "avatarThumbnail": "https://p16-sign-va.tiktokcdn.com/tos-maliva-avt-0068/7326643128006213637~c5_100x100.jpg?lk3s=30310797&nonce=82259&refresh_token=84d3f5c603687bf5fd54093b56b17df0&x-expires=1737212400&x-signature=dRE%2BV0sasY%2B8cdQeMfnuq7uRLzI%3D&shp=30310797&shcp=-"
},
{
  "videoWebUrl": "https://www.tiktok.com/@itsme_lisap/video/7394107845135928619",
  "submittedVideoUrl": "https://www.tiktok.com/@itsme_lisap/video/7394107845135928619",
  "cid": "7394738137714770730",
  "createTime": 1721721721,
  "createTimeISO": "2024-07-23T08:02:01.000Z",
  "text": "💯💯💯",
  "diggCount": 0,
  "repliesToId": null,
  "replyCommentTotal": 0,
  "uid": "6859003216580592645",
  "uniqueId": "anadaaki",
  "avatarThumbnail": "https://p16-sign.tiktokcdn-us.com/tos-useast5-avt-0068-tx/084756596e89cf72663cf201c0590d6a~c5_100x100.jpg?lk3s=30310797&nonce=8498&refresh_token=6a43cecfc1c7a82f8771df7b49278c06&x-expires=1737212400&x-signature=Ft36Td6fPs6UradokDBbT5CD5CM%3D&shp=30310797&shcp=-"
},
{
  "videoWebUrl": "https://www.tiktok.com/@itsme_lisap/video/7394107845135928619",
  "submittedVideoUrl": "https://www.tiktok.com/@itsme_lisap/video/7394107845135928619",
  "cid": "7394148395659920170",
  "createTime": 1721584373,
  "createTimeISO": "2024-07-21T17:52:53.000Z",
  "text": "Too many parents having the mindset of “my life doesn’t have to change bc I have a baby.” Um, yes the fuck it does.",
  "diggCount": 40,
  "repliesToId": null,
  "replyCommentTotal": 3,
  "uid": "6793808794028983301",
  "uniqueId": "alimrojas",
  "avatarThumbnail": "https://p16-sign-va.tiktokcdn.com/tos-maliva-avt-0068/07954e6a7f389860173278db3740b511~c5_100x100.jpg?lk3s=30310797&nonce=83231&refresh_token=f9b1c53d7178de5b6348bf4d7e471a73&x-expires=1737212400&x-signature=0E0yijJBltXSL8%2FhdXklsJ8QP3A%3D&shp=30310797&shcp=-"
},
{
  "videoWebUrl": "https://www.tiktok.com/@itsme_lisap/video/7394107845135928619",
  "submittedVideoUrl": "https://www.tiktok.com/@itsme_lisap/video/7394107845135928619",
  "cid": "7394181365472690986",
  "createTime": 1721592031,
  "createTimeISO": "2024-07-21T20:00:31.000Z",
  "text": "It SHOULD",
  "diggCount": 10,
  "repliesToId": "7394148395659920170",
  "replyCommentTotal": null,
  "uid": "6809686284723897349",
  "uniqueId": "itsme_lisap",
  "avatarThumbnail": "https://p16-sign-va.tiktokcdn.com/tos-maliva-avt-0068/7316683737222086662~c5_100x100.jpg?lk3s=30310797&nonce=91767&refresh_token=9513669c719565e009fe2a9c32cb023d&x-expires=1737212400&x-signature=ooqcviMxUwvTkm2QSu6xZ8miwT4%3D&shp=30310797&shcp=-"
},
{
  "videoWebUrl": "https://www.tiktok.com/@itsme_lisap/video/7394107845135928619",
  "submittedVideoUrl": "https://www.tiktok.com/@itsme_lisap/video/7394107845135928619",
  "cid": "7394575483905770270",
  "createTime": 1721683785,
  "createTimeISO": "2024-07-22T21:29:45.000Z",
  "text": "If people can’t understand this basic concept they shouldn’t have kids. Full stop.",
  "diggCount": 1,
  "repliesToId": null,
  "replyCommentTotal": 0,
  "uid": "6947140160769934342",
  "uniqueId": "crafttacular",
  "avatarThumbnail": "https://p16-sign-va.tiktokcdn.com/tos-maliva-avt-0068/04ca6e41732d140fe75bcd1bb3f26288~c5_100x100.jpg?lk3s=30310797&nonce=13864&refresh_token=fb04fd564971feaca6f9e1a6c20a62d3&x-expires=1737212400&x-signature=LzX5DAK2dj0nwYvE6SLM0FOQY74%3D&shp=30310797&shcp=-"
},
{
  "videoWebUrl": "https://www.tiktok.com/@itsme_lisap/video/7394107845135928619",
  "submittedVideoUrl": "https://www.tiktok.com/@itsme_lisap/video/7394107845135928619",
  "cid": "7398745214439899934",
  "createTime": 1722654614,
  "createTimeISO": "2024-08-03T03:10:14.000Z",
  "text": "There woulda been a fourth of july next year that the poor baby could have attended.",
  "diggCount": 5,
  "repliesToId": null,
  "replyCommentTotal": 0,
  "uid": "75993272761917440",
  "uniqueId": "krazyk00luv",
  "avatarThumbnail": "https://p19-pu-sign-useast8.tiktokcdn-us.com/tos-useast5-avt-0068-tx/7351363991874043946~c5_100x100.jpg?lk3s=30310797&nonce=95018&refresh_token=986b7ac1983e08b9d5c20ad4d277d313&x-expires=1737212400&x-signature=gEgzjCZag2nvVUb2eV4SfbLIT%2F0%3D&shp=30310797&shcp=-"
},
{
  "videoWebUrl": "https://www.tiktok.com/@itsme_lisap/video/7394107845135928619",
  "submittedVideoUrl": "https://www.tiktok.com/@itsme_lisap/video/7394107845135928619",
  "cid": "7394163663097250602",
  "createTime": 1721587907,
  "createTimeISO": "2024-07-21T18:51:47.000Z",
  "text": "I dont get why anyone wants to be out in 120 degrees. That is legitimately dangerous heat, for any human. Especially the young and old.",
  "diggCount": 12,
  "repliesToId": null,
  "replyCommentTotal": 0,
  "uid": "6749731945082913797",
  "uniqueId": "dylan_grass55",
  "avatarThumbnail": "https://p19-pu-sign-useast8.tiktokcdn-us.com/tos-useast5-avt-0068-tx/95f8ad6dc8138eb6b6b553e2d372fc0b~c5_100x100.jpg?lk3s=30310797&nonce=67719&refresh_token=f3d4526549ef5e41f5b64feefce2d68d&x-expires=1737212400&x-signature=W9evw7DSWkxG6ywfqmxFbpQUu2A%3D&shp=30310797&shcp=-"
},
{
  "videoWebUrl": "https://www.tiktok.com/@itsme_lisap/video/7394107845135928619",
  "submittedVideoUrl": "https://www.tiktok.com/@itsme_lisap/video/7394107845135928619",
  "cid": "7394109337788924714",
  "createTime": 1721575271,
  "createTimeISO": "2024-07-21T15:21:11.000Z",
  "text": "What happened to that baby is criminal. Imagine if it was a family of color or a minority.",
  "diggCount": 28,
  "repliesToId": null,
  "replyCommentTotal": 0,
  "uid": "6780423835731051525",
  "uniqueId": "theavaporisoffical",
  "avatarThumbnail": "https://p16-sign.tiktokcdn-us.com/tos-useast5-avt-0068-tx/7314377832480636971~c5_100x100.jpg?lk3s=30310797&nonce=57351&refresh_token=0e54aa36216b55b00fa790d251498f63&x-expires=1737212400&x-signature=ZSFfF6R8TK5HHYXM6K%2BJkNSMKUI%3D&shp=30310797&shcp=-"
},
{
  "videoWebUrl": "https://www.tiktok.com/@itsme_lisap/video/7394107845135928619",
  "submittedVideoUrl": "https://www.tiktok.com/@itsme_lisap/video/7394107845135928619",
  "cid": "7394166655415124778",
  "createTime": 1721588616,
  "createTimeISO": "2024-07-21T19:03:36.000Z",
  "text": "This was a choice they intentionally neglected this baby and she died.",
  "diggCount": 10,
  "repliesToId": null,
  "replyCommentTotal": 0,
  "uid": "6997875662314095622",
  "uniqueId": "shay621184",
  "avatarThumbnail": "https://p16-sign-va.tiktokcdn.com/tos-maliva-avt-0068/500db6f773a1faf333dd7771a3217143~c5_100x100.jpg?lk3s=30310797&nonce=1890&refresh_token=26aeb6faf3080e60115fc75999ef7f60&x-expires=1737212400&x-signature=FM5F6GkO6oLHvGVzldFXVvzDv58%3D&shp=30310797&shcp=-"
},
{
  "videoWebUrl": "https://www.tiktok.com/@itsme_lisap/video/7394107845135928619",
  "submittedVideoUrl": "https://www.tiktok.com/@itsme_lisap/video/7394107845135928619",
  "cid": "7394156254518264618",
  "createTime": 1721586227,
  "createTimeISO": "2024-07-21T18:23:47.000Z",
  "text": "You miss out when you have children. Period. It’s simple. Your job as a parent is to be selfless not selfish.",
  "diggCount": 9,
  "repliesToId": null,
  "replyCommentTotal": 0,
  "uid": "6995616287452742662",
  "uniqueId": "aksandbach",
  "avatarThumbnail": "https://p19-pu-sign-useast8.tiktokcdn-us.com/tos-useast5-avt-0068-tx/9e0832f115d261a2338000c22314c152~c5_100x100.jpg?lk3s=30310797&nonce=11416&refresh_token=0ccde088373bde2687b4e0a785f138c5&x-expires=1737212400&x-signature=FR9KCo2PqCDhHe33aDU2s76WTlE%3D&shp=30310797&shcp=-"
},
{
  "videoWebUrl": "https://www.tiktok.com/@itsme_lisap/video/7394107845135928619",
  "submittedVideoUrl": "https://www.tiktok.com/@itsme_lisap/video/7394107845135928619",
  "cid": "7394162095472362271",
  "createTime": 1721587541,
  "createTimeISO": "2024-07-21T18:45:41.000Z",
  "text": "AZ native here. they should absolutely be charged for this but won't because the man's a cop",
  "diggCount": 7,
  "repliesToId": null,
  "replyCommentTotal": 0,
  "uid": "6857588185363465222",
  "uniqueId": "londonbrainfog",
  "avatarThumbnail": "https://p19-pu-sign-useast8.tiktokcdn-us.com/tos-useast8-avt-0068-tx2/ec3909833d84d7f34c1f20750d127d05~c5_100x100.jpg?lk3s=30310797&nonce=59669&refresh_token=2079f1ddf9df467c89dc416767322f4e&x-expires=1737212400&x-signature=dIQGfk%2FeUbNrb%2BuFie%2B63o9ajUg%3D&shp=30310797&shcp=-"
},
{
  "videoWebUrl": "https://www.tiktok.com/@itsme_lisap/video/7394107845135928619",
  "submittedVideoUrl": "https://www.tiktok.com/@itsme_lisap/video/7394107845135928619",
  "cid": "7394122269343351583",
  "createTime": 1721578267,
  "createTimeISO": "2024-07-21T16:11:07.000Z",
  "text": "let's pretend you didn't know babies can't regulate their own temp, 120* is outrageous!!!! EVERYONE knows that's too hot to be outside for hours!",
  "diggCount": 12,
  "repliesToId": null,
  "replyCommentTotal": 0,
  "uid": "6823978432859636742",
  "uniqueId": "jburrrrrr",
  "avatarThumbnail": "https://p16-sign-va.tiktokcdn.com/tos-maliva-avt-0068/7327704485307973637~c5_100x100.jpg?lk3s=30310797&nonce=37852&refresh_token=e46a0ed093e8246ea0e8e3c4f680f6a2&x-expires=1737212400&x-signature=va5qETkXvm5XOl0zJUJYLBoKgtI%3D&shp=30310797&shcp=-"
},
{
  "videoWebUrl": "https://www.tiktok.com/@itsme_lisap/video/7394107845135928619",
  "submittedVideoUrl": "https://www.tiktok.com/@itsme_lisap/video/7394107845135928619",
  "cid": "7394113410121646890",
  "createTime": 1721576213,
  "createTimeISO": "2024-07-21T15:36:53.000Z",
  "text": "I completely agree. I would even argue that they made many, MANY dangerous decisions. Repeatedly.",
  "diggCount": 8,
  "repliesToId": null,
  "replyCommentTotal": 0,
  "uid": "6825336663837901829",
  "uniqueId": "annxbt014",
  "avatarThumbnail": "https://p16-pu-sign-useast8.tiktokcdn-us.com/tos-useast5-avt-0068-tx/2ec891bbdb7bef3133b19aa85492e30a~c5_100x100.jpg?lk3s=30310797&nonce=22582&refresh_token=3c88395541df0054005d11929f840fd1&x-expires=1737212400&x-signature=NtuCyOb4PWOaWfKFl6ZMyoGe5eI%3D&shp=30310797&shcp=-"
},
{
  "videoWebUrl": "https://www.tiktok.com/@itsme_lisap/video/7394107845135928619",
  "submittedVideoUrl": "https://www.tiktok.com/@itsme_lisap/video/7394107845135928619",
  "cid": "7394112852417594144",
  "createTime": 1721576066,
  "createTimeISO": "2024-07-21T15:34:26.000Z",
  "text": "And again I wonder how we need a license to operate cars but having kids is just „here, enjoy, good luck“",
  "diggCount": 6,
  "repliesToId": null,
  "replyCommentTotal": 0,
  "uid": "6980348644965745670",
  "uniqueId": "nadch0603",
  "avatarThumbnail": "https://p16-sign-va.tiktokcdn.com/tos-maliva-avt-0068/a41dbe7171e7a567cb9904c3fef8c7b7~c5_100x100.jpg?lk3s=30310797&nonce=55786&refresh_token=c493b3f78288656aa7cc991e82aa23f0&x-expires=1737212400&x-signature=rPIFlkfT1OQpzSFezud%2BzgWZj6I%3D&shp=30310797&shcp=-"
},
{
  "videoWebUrl": "https://www.tiktok.com/@itsme_lisap/video/7394107845135928619",
  "submittedVideoUrl": "https://www.tiktok.com/@itsme_lisap/video/7394107845135928619",
  "cid": "7400105585163010846",
  "createTime": 1722971352,
  "createTimeISO": "2024-08-06T19:09:12.000Z",
  "text": "Plus, their misguided decision to bring her in that life jacket probably contributed to her heat stroke. Poor little girl! Can you imagine how hot you would feel?",
  "diggCount": 2,
  "repliesToId": null,
  "replyCommentTotal": 0,
  "uid": "6953785539377005574",
  "uniqueId": "shadow2reiter",
  "avatarThumbnail": "https://p16-pu-sign-useast8.tiktokcdn-us.com/tos-useast5-avt-0068-tx/7344938057923035182~c5_100x100.jpg?lk3s=30310797&nonce=60417&refresh_token=515a92a8a392130d4f5775bf24aba242&x-expires=1737212400&x-signature=ZPYnwmFb7anCXUSiWDIqIxgaBBU%3D&shp=30310797&shcp=-"
},
{
  "videoWebUrl": "https://www.tiktok.com/@itsme_lisap/video/7394107845135928619",
  "submittedVideoUrl": "https://www.tiktok.com/@itsme_lisap/video/7394107845135928619",
  "cid": "7394247226559939370",
  "createTime": 1721607367,
  "createTimeISO": "2024-07-22T00:16:07.000Z",
  "text": "I didn’t even take my 4 year old to see fireworks cuz it was 108 (it would’ve been after sunset with shade).",
  "diggCount": 4,
  "repliesToId": null,
  "replyCommentTotal": 0,
  "uid": "7154134316669862958",
  "uniqueId": "bellestar37",
  "avatarThumbnail": "https://p19-pu-sign-useast8.tiktokcdn-us.com/tos-useast5-avt-0068-tx/2096bd01e6d7bd43913523b335f21d9e~c5_100x100.jpg?lk3s=30310797&nonce=54440&refresh_token=99313b5edee7b5bca00813c62812af68&x-expires=1737212400&x-signature=hAf3B3KjXq8TCkUpXdto1y%2BkuDU%3D&shp=30310797&shcp=-"
},
{
  "videoWebUrl": "https://www.tiktok.com/@itsme_lisap/video/7394107845135928619",
  "submittedVideoUrl": "https://www.tiktok.com/@itsme_lisap/video/7394107845135928619",
  "cid": "7394206234230244138",
  "createTime": 1721597816,
  "createTimeISO": "2024-07-21T21:36:56.000Z",
  "text": "I don't have kids. Idk things like when they start eating solids, when they start vaccines etc. Point is that it's still obvious to me that a child in hot weather they can't escape is a bad idea..",
  "diggCount": 4,
  "repliesToId": null,
  "replyCommentTotal": 0,
  "uid": "7001668497495573509",
  "uniqueId": "stephanieblasyak80",
  "avatarThumbnail": "https://p19-pu-sign-useast8.tiktokcdn-us.com/tos-useast5-avt-0068-tx/7322008779040489515~c5_100x100.jpg?lk3s=30310797&nonce=32151&refresh_token=4cb839045752404b0643cdfecd23aa19&x-expires=1737212400&x-signature=LtZFde%2BXm5dKsUURjnZctKs0Dzw%3D&shp=30310797&shcp=-"
},
{
  "videoWebUrl": "https://www.tiktok.com/@itsme_lisap/video/7394107845135928619",
  "submittedVideoUrl": "https://www.tiktok.com/@itsme_lisap/video/7394107845135928619",
  "cid": "7394191737566954283",
  "createTime": 1721594457,
  "createTimeISO": "2024-07-21T20:40:57.000Z",
  "text": "“There is no way that baby had any business being outside” PERIOD FULL SENTENCE. No person should be out in 120 weather, ESPECIALLY a baby. Any time amount. That poor little angel",
  "diggCount": 4,
  "repliesToId": null,
  "replyCommentTotal": 0,
  "uid": "6915197120505299973",
  "uniqueId": "moe.makes.magick",
  "avatarThumbnail": "https://p16-pu-sign-useast8.tiktokcdn-us.com/tos-useast5-avt-0068-tx/500704e9f0b190b5bef18b49d68cc6ab~c5_100x100.jpg?lk3s=30310797&nonce=5445&refresh_token=2f05efe8d914934a4fa50a514c0a25d2&x-expires=1737212400&x-signature=fWildK7Xovvr7JtWLwyiCzUn9gk%3D&shp=30310797&shcp=-"
},
{
  "videoWebUrl": "https://www.tiktok.com/@itsme_lisap/video/7394107845135928619",
  "submittedVideoUrl": "https://www.tiktok.com/@itsme_lisap/video/7394107845135928619",
  "cid": "7398009978835419935",
  "createTime": 1722483428,
  "createTimeISO": "2024-08-01T03:37:08.000Z",
  "text": "If it’s even over like 80 we don’t even bring our CHIHUAHUA on the boat.",
  "diggCount": 1,
  "repliesToId": null,
  "replyCommentTotal": 0,
  "uid": "6816024104617985029",
  "uniqueId": "fb26364646",
  "avatarThumbnail": "https://p19-pu-sign-useast8.tiktokcdn-us.com/tos-useast8-avt-0068-tx2/fb907dd2266f1872086e6c1caaf82aa0~c5_100x100.jpg?lk3s=30310797&nonce=53826&refresh_token=527334974c54efe6c255988ebeef34f0&x-expires=1737212400&x-signature=RB13ty64YvPhBQg%2FoudqPwNOYH0%3D&shp=30310797&shcp=-"
},
{
  "videoWebUrl": "https://www.tiktok.com/@itsme_lisap/video/7394107845135928619",
  "submittedVideoUrl": "https://www.tiktok.com/@itsme_lisap/video/7394107845135928619",
  "cid": "7394308672774669089",
  "createTime": 1721621788,
  "createTimeISO": "2024-07-22T04:16:28.000Z",
  "text": "And yet the parents set up a go fund me page to make money of their cruelty to their lost child…I think it was at around $50k when someone I follow spoke about it the other day. Disgusting.",
  "diggCount": 2,
  "repliesToId": null,
  "replyCommentTotal": 1,
  "uid": "6687238854338970629",
  "uniqueId": "louloukins01",
  "avatarThumbnail": "https://p16-sign-useast2a.tiktokcdn.com/tos-useast2a-avt-0068-euttp/e5cd3a6efd593b7d68b96e9b2a45fd35~c5_100x100.jpg?lk3s=30310797&nonce=34335&refresh_token=c58091ae7322d44115f035ea446ec893&x-expires=1737212400&x-signature=7IVYhNBoCNO%2By9yMOqi07gqOUyk%3D&shp=30310797&shcp=-"
},
{
  "videoWebUrl": "https://www.tiktok.com/@itsme_lisap/video/7394107845135928619",
  "submittedVideoUrl": "https://www.tiktok.com/@itsme_lisap/video/7394107845135928619",
  "cid": "7394168555091313440",
  "createTime": 1721589049,
  "createTimeISO": "2024-07-21T19:10:49.000Z",
  "text": "It’s just wild cause you spend so much time as a parent being paranoid I cannot imagine this",
  "diggCount": 4,
  "repliesToId": null,
  "replyCommentTotal": 2,
  "uid": "6786041335481926661",
  "uniqueId": "tishtoking",
  "avatarThumbnail": "https://p16-sign-useast2a.tiktokcdn.com/tos-useast2a-avt-0068-euttp/3bf0d63ebf5edfe4026b09566add92c5~c5_100x100.jpg?lk3s=30310797&nonce=63629&refresh_token=c8be066a2d2e27849794307cc08afa16&x-expires=1737212400&x-signature=gESBP%2B%2Brl3NHkWNG4rGKPqOq5tc%3D&shp=30310797&shcp=-"
},
{
  "videoWebUrl": "https://www.tiktok.com/@itsme_lisap/video/7394107845135928619",
  "submittedVideoUrl": "https://www.tiktok.com/@itsme_lisap/video/7394107845135928619",
  "cid": "7394180975511405358",
  "createTime": 1721591941,
  "createTimeISO": "2024-07-21T19:59:01.000Z",
  "text": "I can’t either. I just…it’s baffling",
  "diggCount": 3,
  "repliesToId": "7394168555091313440",
  "replyCommentTotal": null,
  "uid": "6809686284723897349",
  "uniqueId": "itsme_lisap",
  "avatarThumbnail": "https://p16-sign-va.tiktokcdn.com/tos-maliva-avt-0068/7316683737222086662~c5_100x100.jpg?lk3s=30310797&nonce=91767&refresh_token=9513669c719565e009fe2a9c32cb023d&x-expires=1737212400&x-signature=ooqcviMxUwvTkm2QSu6xZ8miwT4%3D&shp=30310797&shcp=-"
},
{
  "videoWebUrl": "https://www.tiktok.com/@itsme_lisap/video/7394107845135928619",
  "submittedVideoUrl": "https://www.tiktok.com/@itsme_lisap/video/7394107845135928619",
  "cid": "7398042162909610783",
  "createTime": 1722490926,
  "createTimeISO": "2024-08-01T05:42:06.000Z",
  "text": "lived in LHC a few dif xs. 1st of all- min u walk outside ur burning tf up @ 130°! left baby ON BOAT swaddled asf! wtf!? 130° becomes 100xs hotter on water. I don't understand how they did this!? 🥺",
  "diggCount": 1,
  "repliesToId": null,
  "replyCommentTotal": 0,
  "uid": "6981946457713263622",
  "uniqueId": "casslovering",
  "avatarThumbnail": "https://p19-sign.tiktokcdn-us.com/tos-useast5-avt-0068-tx/940835147e1c1bfd2bc456f1c2e18fa7~c5_100x100.jpg?lk3s=30310797&nonce=31876&refresh_token=047866e0d61ff49faabeda8e20450d13&x-expires=1737212400&x-signature=DlfzdVRe36BjSmBhtpBZjKpJHpI%3D&shp=30310797&shcp=-"
},
{
  "videoWebUrl": "https://www.tiktok.com/@itsme_lisap/video/7394107845135928619",
  "submittedVideoUrl": "https://www.tiktok.com/@itsme_lisap/video/7394107845135928619",
  "cid": "7394319006146691871",
  "createTime": 1721624080,
  "createTimeISO": "2024-07-22T04:54:40.000Z",
  "text": "The fact that the dad is a Detective for Riverside county! Where is the supposed investigation?! Their older child should be taken from them! 😡😡😡",
  "diggCount": 2,
  "repliesToId": null,
  "replyCommentTotal": 5,
  "uid": "6812110754172863493",
  "uniqueId": "igrayyy88",
  "avatarThumbnail": "https://p16-pu-sign-useast8.tiktokcdn-us.com/tos-useast5-avt-0068-tx/7315213431412375598~c5_100x100.jpg?lk3s=30310797&nonce=341&refresh_token=5f8eb6982541005ba76cacbdefb3c095&x-expires=1737212400&x-signature=45Z%2BQzRLDPT5MBmHUptCw8ZUNBY%3D&shp=30310797&shcp=-"
},
{
  "videoWebUrl": "https://www.tiktok.com/@itsme_lisap/video/7394107845135928619",
  "submittedVideoUrl": "https://www.tiktok.com/@itsme_lisap/video/7394107845135928619",
  "cid": "7394179541005550367",
  "createTime": 1721591610,
  "createTimeISO": "2024-07-21T19:53:30.000Z",
  "text": "Immediate murder charge. Those parents knew what they were doing.",
  "diggCount": 2,
  "repliesToId": null,
  "replyCommentTotal": 1,
  "uid": "6788496199101875205",
  "uniqueId": "irinad56",
  "avatarThumbnail": "https://p16-sign-va.tiktokcdn.com/tos-maliva-avt-0068/7334483206689554437~c5_100x100.jpg?lk3s=30310797&nonce=82854&refresh_token=6cc7f37706cf75637d4a11f981ff93dd&x-expires=1737212400&x-signature=CmoMCNroqUolbHcsci1SkWmxSYo%3D&shp=30310797&shcp=-"
},
{
  "videoWebUrl": "https://www.tiktok.com/@itsme_lisap/video/7394107845135928619",
  "submittedVideoUrl": "https://www.tiktok.com/@itsme_lisap/video/7394107845135928619",
  "cid": "7394645504749880107",
  "createTime": 1721700099,
  "createTimeISO": "2024-07-23T02:01:39.000Z",
  "text": "This wasn’t the only child that died that week in Arizona. There were 3-4 and all were due to the heat. It’s so infuriating.",
  "diggCount": 1,
  "repliesToId": null,
  "replyCommentTotal": 0,
  "uid": "6806517722181272582",
  "uniqueId": "tameckanave",
  "avatarThumbnail": "https://p16-sign-va.tiktokcdn.com/tos-maliva-avt-0068/7322668679236648966~c5_100x100.jpg?lk3s=30310797&nonce=15183&refresh_token=8c6424c5fd442c47a3552195d1e20aaa&x-expires=1737212400&x-signature=q1tdeEsfLCZzMGV5B1k27SDb7CM%3D&shp=30310797&shcp=-"
},
{
  "videoWebUrl": "https://www.tiktok.com/@itsme_lisap/video/7394107845135928619",
  "submittedVideoUrl": "https://www.tiktok.com/@itsme_lisap/video/7394107845135928619",
  "cid": "7394306224204432174",
  "createTime": 1721621124,
  "createTimeISO": "2024-07-22T04:05:24.000Z",
  "text": "The parents should be legally held responsible. Poor baby was suffering because mom and dad just HAVE to have their fun time!",
  "diggCount": 1,
  "repliesToId": null,
  "replyCommentTotal": 0,
  "uid": "6829375558444057606",
  "uniqueId": "qtmami2000",
  "avatarThumbnail": "https://p19-pu-sign-useast8.tiktokcdn-us.com/tos-useast5-avt-0068-tx/7351490827127881770~c5_100x100.jpg?lk3s=30310797&nonce=67238&refresh_token=05a1d6f41c6d8527a147d995bd17f3a6&x-expires=1737212400&x-signature=ZoM8G4jrDciflZp2mHy8xHagtSw%3D&shp=30310797&shcp=-"
},
{
  "videoWebUrl": "https://www.tiktok.com/@itsme_lisap/video/7394107845135928619",
  "submittedVideoUrl": "https://www.tiktok.com/@itsme_lisap/video/7394107845135928619",
  "cid": "7394876158480941855",
  "createTime": 1721753798,
  "createTimeISO": "2024-07-23T16:56:38.000Z",
  "text": "OMG NOOOOOO. Utah has been ROASTING - stay home! Don’t hike this year, it’ll be there next year. 💔💔💔",
  "diggCount": 1,
  "repliesToId": null,
  "replyCommentTotal": 2,
  "uid": "6749196148391199750",
  "uniqueId": "amongtheyoung",
  "avatarThumbnail": "https://p19-pu-sign-useast8.tiktokcdn-us.com/tos-useast8-avt-0068-tx2/5d1564f965935ad7b9c23bc25293ce4d~c5_100x100.jpg?lk3s=30310797&nonce=88425&refresh_token=28aeed93a60554bfe986f48ad0372c18&x-expires=1737212400&x-signature=T71nUL3%2BGyen4wSN7O01AaOHQnk%3D&shp=30310797&shcp=-"
},
{
  "videoWebUrl": "https://www.tiktok.com/@itsme_lisap/video/7394107845135928619",
  "submittedVideoUrl": "https://www.tiktok.com/@itsme_lisap/video/7394107845135928619",
  "cid": "7394936936861860651",
  "createTime": 1721767955,
  "createTimeISO": "2024-07-23T20:52:35.000Z",
  "text": "Exactly! This is a record heat year! Keep the babies home",
  "diggCount": 1,
  "repliesToId": "7394876158480941855",
  "replyCommentTotal": null,
  "uid": "6809686284723897349",
  "uniqueId": "itsme_lisap",
  "avatarThumbnail": "https://p16-sign-va.tiktokcdn.com/tos-maliva-avt-0068/7316683737222086662~c5_100x100.jpg?lk3s=30310797&nonce=91767&refresh_token=9513669c719565e009fe2a9c32cb023d&x-expires=1737212400&x-signature=ooqcviMxUwvTkm2QSu6xZ8miwT4%3D&shp=30310797&shcp=-"
},
{
  "videoWebUrl": "https://www.tiktok.com/@itsme_lisap/video/7394107845135928619",
  "submittedVideoUrl": "https://www.tiktok.com/@itsme_lisap/video/7394107845135928619",
  "cid": "7394110078083810090",
  "createTime": 1721575457,
  "createTimeISO": "2024-07-21T15:24:17.000Z",
  "text": "Oh! We were talking about this with my kids just yesterday!! (They are both your age-ish with 4 kids between them). This story is maddening. Parents were NOT parenting. You are 💯 correct!!!",
  "diggCount": 3,
  "repliesToId": null,
  "replyCommentTotal": 0,
  "uid": "6762998671828354054",
  "uniqueId": "legalmom2",
  "avatarThumbnail": "https://p16-sign-va.tiktokcdn.com/tos-maliva-avt-0068/7331588297094856709~c5_100x100.jpg?lk3s=30310797&nonce=42674&refresh_token=5ca784e730e8fdb8a07e524265cd0bc7&x-expires=1737212400&x-signature=D3X22kcQpZf3P9FWItRI%2F8vDNOU%3D&shp=30310797&shcp=-"
},
{
  "videoWebUrl": "https://www.tiktok.com/@itsme_lisap/video/7394107845135928619",
  "submittedVideoUrl": "https://www.tiktok.com/@itsme_lisap/video/7394107845135928619",
  "cid": "7398363462054937375",
  "createTime": 1722565730,
  "createTimeISO": "2024-08-02T02:28:50.000Z",
  "text": "I actually cried !!!!!",
  "diggCount": 0,
  "repliesToId": null,
  "replyCommentTotal": 0,
  "uid": "7293374111811453995",
  "uniqueId": "cougargreenzaz",
  "avatarThumbnail": "https://p16-sign-va.tiktokcdn.com/tos-maliva-avt-0068/f14f4e3b394375380bd2e94aef85724d~c5_100x100.jpg?lk3s=30310797&nonce=78369&refresh_token=c9d8de4d0562f3f9f838582601cf6f89&x-expires=1737212400&x-signature=Hf%2BwNjE8IV4kcg55yob9ACAnuKM%3D&shp=30310797&shcp=-"
},
{
  "videoWebUrl": "https://www.tiktok.com/@itsme_lisap/video/7394107845135928619",
  "submittedVideoUrl": "https://www.tiktok.com/@itsme_lisap/video/7394107845135928619",
  "cid": "7394199950425113374",
  "createTime": 1721596357,
  "createTimeISO": "2024-07-21T21:12:37.000Z",
  "text": "Completely agree.",
  "diggCount": 0,
  "repliesToId": null,
  "replyCommentTotal": 0,
  "uid": "7015239572615660550",
  "uniqueId": "poseysmama",
  "avatarThumbnail": "https://p16-sign-va.tiktokcdn.com/tos-maliva-avt-0068/5272e202264c3bd7708ee84b71f3c215~c5_100x100.jpg?lk3s=30310797&nonce=84125&refresh_token=f75bbf788b9085dc825cde12cec3bda8&x-expires=1737212400&x-signature=StZDWPilq5Kprc8FhWva4oTwsyw%3D&shp=30310797&shcp=-"
},
{
  "videoWebUrl": "https://www.tiktok.com/@itsme_lisap/video/7394107845135928619",
  "submittedVideoUrl": "https://www.tiktok.com/@itsme_lisap/video/7394107845135928619",
  "cid": "7394177309274964766",
  "createTime": 1721591089,
  "createTimeISO": "2024-07-21T19:44:49.000Z",
  "text": "This 100 percent. I hear it all the time.",
  "diggCount": 0,
  "repliesToId": "7394148395659920170",
  "replyCommentTotal": null,
  "uid": "6809980897053885446",
  "uniqueId": "mariawouldntwannabeya23",
  "avatarThumbnail": "https://p19-pu-sign-useast8.tiktokcdn-us.com/tos-useast8-avt-0068-tx2/9da5c8ea6fd508a1fddda25c7bf80e65~c5_100x100.jpg?lk3s=30310797&nonce=70969&refresh_token=1b16ed106e6377e2e5f00edac633c03c&x-expires=1737212400&x-signature=eCIDXHfnWxJAxVnl8%2B3Noxtq4lw%3D&shp=30310797&shcp=-"
},
{
  "videoWebUrl": "https://www.tiktok.com/@itsme_lisap/video/7394107845135928619",
  "submittedVideoUrl": "https://www.tiktok.com/@itsme_lisap/video/7394107845135928619",
  "cid": "7396045929193669419",
  "createTime": 1722026178,
  "createTimeISO": "2024-07-26T20:36:18.000Z",
  "text": "Exactly if you don’t wanna care for a baby don’t have one",
  "diggCount": 0,
  "repliesToId": "7394148395659920170",
  "replyCommentTotal": null,
  "uid": "6798221044399637509",
  "uniqueId": "illfollowyouintothedark",
  "avatarThumbnail": "https://p19-pu-sign-useast8.tiktokcdn-us.com/tos-useast5-avt-0068-tx/e691598c4dc3261ba6f6b4c9686f3075~c5_100x100.jpg?lk3s=30310797&nonce=78848&refresh_token=1f23fd7fe5880e6e849d184083cdf832&x-expires=1737212400&x-signature=s%2BEkonjaye7jPHr7PkFnzfflBRY%3D&shp=30310797&shcp=-"
},
{
  "videoWebUrl": "https://www.tiktok.com/@itsme_lisap/video/7394107845135928619",
  "submittedVideoUrl": "https://www.tiktok.com/@itsme_lisap/video/7394107845135928619",
  "cid": "7394570373161780014",
  "createTime": 1721682611,
  "createTimeISO": "2024-07-22T21:10:11.000Z",
  "text": "The gofundme got taken down but who knows if all those people that donated got their money back.",
  "diggCount": 1,
  "repliesToId": "7394308672774669089",
  "replyCommentTotal": null,
  "uid": "6641385705300918277",
  "uniqueId": "angiesmami10",
  "avatarThumbnail": "https://p19-pu-sign-useast8.tiktokcdn-us.com/tos-useast5-avt-0068-tx/7348828145732042798~c5_100x100.jpg?lk3s=30310797&nonce=96193&refresh_token=9b6d08e0760c11b01f680f287904b0e3&x-expires=1737212400&x-signature=eR1ab3528v%2BB8nppQ2Xys82oQAY%3D&shp=30310797&shcp=-"
},
{
  "videoWebUrl": "https://www.tiktok.com/@itsme_lisap/video/7394107845135928619",
  "submittedVideoUrl": "https://www.tiktok.com/@itsme_lisap/video/7394107845135928619",
  "cid": "7394183925264466720",
  "createTime": 1721592619,
  "createTimeISO": "2024-07-21T20:10:19.000Z",
  "text": "This is why we shouldn’t glorify parenting like it’s not easy you have to sacrifice majority of your life. This is biggest responsibility of your life",
  "diggCount": 0,
  "repliesToId": "7394168555091313440",
  "replyCommentTotal": null,
  "uid": "6786041335481926661",
  "uniqueId": "tishtoking",
  "avatarThumbnail": "https://p16-sign-useast2a.tiktokcdn.com/tos-useast2a-avt-0068-euttp/3bf0d63ebf5edfe4026b09566add92c5~c5_100x100.jpg?lk3s=30310797&nonce=14968&refresh_token=90444e28a7db317857e51c156f8644d7&x-expires=1737212400&x-signature=gESBP%2B%2Brl3NHkWNG4rGKPqOq5tc%3D&shp=30310797&shcp=-"
},
{
  "videoWebUrl": "https://www.tiktok.com/@itsme_lisap/video/7394107845135928619",
  "submittedVideoUrl": "https://www.tiktok.com/@itsme_lisap/video/7394107845135928619",
  "cid": "7394570238614602542",
  "createTime": 1721682568,
  "createTimeISO": "2024-07-22T21:09:28.000Z",
  "text": "it's been over 2 weeks and no charges. Makes me ill.",
  "diggCount": 0,
  "repliesToId": "7394179541005550367",
  "replyCommentTotal": null,
  "uid": "6641385705300918277",
  "uniqueId": "angiesmami10",
  "avatarThumbnail": "https://p16-sign-va.tiktokcdn.com/tos-maliva-avt-0068/7348828145732042798~c5_100x100.jpg?lk3s=30310797&nonce=85448&refresh_token=0a0cf8590c0a3380c4fcefe7d5ae5aa6&x-expires=1737212400&x-signature=zESdq963llX%2B0dO0lzmZ8RJlY9w%3D&shp=30310797&shcp=-"
},
{
  "videoWebUrl": "https://www.tiktok.com/@itsme_lisap/video/7394107845135928619",
  "submittedVideoUrl": "https://www.tiktok.com/@itsme_lisap/video/7394107845135928619",
  "cid": "7394560241811653422",
  "createTime": 1721680259,
  "createTimeISO": "2024-07-22T20:30:59.000Z",
  "text": "They are being investigated by Mojave county sheriffs",
  "diggCount": 0,
  "repliesToId": "7394319006146691871",
  "replyCommentTotal": null,
  "uid": "7368965321272411182",
  "uniqueId": "madissyh1h8",
  "avatarThumbnail": "https://p16-sign-va.tiktokcdn.com/musically-maliva-obj/1594805258216454~c5_100x100.jpg?lk3s=30310797&nonce=81246&refresh_token=fff9e774c691240f7e20dda99bc5ee88&x-expires=1737212400&x-signature=sj5DVp7Hy7TTQGluyFHHs7MACmM%3D&shp=30310797&shcp=-"
},
{
  "videoWebUrl": "https://www.tiktok.com/@itsme_lisap/video/7394107845135928619",
  "submittedVideoUrl": "https://www.tiktok.com/@itsme_lisap/video/7394107845135928619",
  "cid": "7394570807890379562",
  "createTime": 1721682702,
  "createTimeISO": "2024-07-22T21:11:42.000Z",
  "text": "do these investigations usually take longer than 2 weeks? ☹️",
  "diggCount": 1,
  "repliesToId": "7394319006146691871",
  "replyCommentTotal": null,
  "uid": "6641385705300918277",
  "uniqueId": "angiesmami10",
  "avatarThumbnail": "https://p16-pu-sign-useast8.tiktokcdn-us.com/tos-useast5-avt-0068-tx/7348828145732042798~c5_100x100.jpg?lk3s=30310797&nonce=24278&refresh_token=a5bda16efd6ee716ee3fdfa5fcd1cadf&x-expires=1737212400&x-signature=YHJmO0S3cF%2Bgnmg9irtvCkjAh%2F4%3D&shp=30310797&shcp=-"
},
{
  "videoWebUrl": "https://www.tiktok.com/@itsme_lisap/video/7394107845135928619",
  "submittedVideoUrl": "https://www.tiktok.com/@itsme_lisap/video/7394107845135928619",
  "cid": "7394574886339986207",
  "createTime": 1721683652,
  "createTimeISO": "2024-07-22T21:27:32.000Z",
  "text": "Yes, on top of the coroners report about the autopsy and gathering all information from witnesses and interviews.",
  "diggCount": 2,
  "repliesToId": "7394319006146691871",
  "replyCommentTotal": null,
  "uid": "7368965321272411182",
  "uniqueId": "madissyh1h8",
  "avatarThumbnail": "https://p16-sign-va.tiktokcdn.com/musically-maliva-obj/1594805258216454~c5_100x100.jpg?lk3s=30310797&nonce=81246&refresh_token=fff9e774c691240f7e20dda99bc5ee88&x-expires=1737212400&x-signature=sj5DVp7Hy7TTQGluyFHHs7MACmM%3D&shp=30310797&shcp=-"
},
{
  "videoWebUrl": "https://www.tiktok.com/@itsme_lisap/video/7394107845135928619",
  "submittedVideoUrl": "https://www.tiktok.com/@itsme_lisap/video/7394107845135928619",
  "cid": "7394575243732026154",
  "createTime": 1721683738,
  "createTimeISO": "2024-07-22T21:28:58.000Z",
  "text": "Yeah that's true. Thanks.",
  "diggCount": 1,
  "repliesToId": "7394319006146691871",
  "replyCommentTotal": null,
  "uid": "6641385705300918277",
  "uniqueId": "angiesmami10",
  "avatarThumbnail": "https://p16-pu-sign-useast8.tiktokcdn-us.com/tos-useast5-avt-0068-tx/7348828145732042798~c5_100x100.jpg?lk3s=30310797&nonce=24278&refresh_token=a5bda16efd6ee716ee3fdfa5fcd1cadf&x-expires=1737212400&x-signature=YHJmO0S3cF%2Bgnmg9irtvCkjAh%2F4%3D&shp=30310797&shcp=-"
},
{
  "videoWebUrl": "https://www.tiktok.com/@itsme_lisap/video/7394107845135928619",
  "submittedVideoUrl": "https://www.tiktok.com/@itsme_lisap/video/7394107845135928619",
  "cid": "7394560320940147498",
  "createTime": 1721680276,
  "createTimeISO": "2024-07-22T20:31:16.000Z",
  "text": "Since it happened in Arizona",
  "diggCount": 0,
  "repliesToId": "7394319006146691871",
  "replyCommentTotal": null,
  "uid": "7368965321272411182",
  "uniqueId": "madissyh1h8",
  "avatarThumbnail": "https://p16-sign-va.tiktokcdn.com/musically-maliva-obj/1594805258216454~c5_100x100.jpg?lk3s=30310797&nonce=81246&refresh_token=fff9e774c691240f7e20dda99bc5ee88&x-expires=1737212400&x-signature=sj5DVp7Hy7TTQGluyFHHs7MACmM%3D&shp=30310797&shcp=-"
},
{
  "videoWebUrl": "https://www.tiktok.com/@itsme_lisap/video/7394107845135928619",
  "submittedVideoUrl": "https://www.tiktok.com/@itsme_lisap/video/7394107845135928619",
  "cid": "7396424086295462687",
  "createTime": 1722114210,
  "createTimeISO": "2024-07-27T21:03:30.000Z",
  "text": "💔💔💔",
  "diggCount": 0,
  "repliesToId": "7394876158480941855",
  "replyCommentTotal": null,
  "uid": "6749196148391199750",
  "uniqueId": "amongtheyoung",
  "avatarThumbnail": "https://p16-pu-sign-useast8.tiktokcdn-us.com/tos-useast8-avt-0068-tx2/5d1564f965935ad7b9c23bc25293ce4d~c5_100x100.jpg?lk3s=30310797&nonce=22648&refresh_token=b574976f94465a0921d92ee7d54fb2d0&x-expires=1737212400&x-signature=v1fT7t0Dg%2BV9uCcINwCm89iXrtE%3D&shp=30310797&shcp=-"
},
{
  "videoWebUrl": "https://www.tiktok.com/@itsme_lisap/video/7394107845135928619",
  "submittedVideoUrl": "https://www.tiktok.com/@itsme_lisap/video/7394107845135928619",
  "cid": "7394171803844035360",
  "createTime": 1721589810,
  "createTimeISO": "2024-07-21T19:23:30.000Z",
  "text": "Murder by heat",
  "diggCount": 1,
  "repliesToId": null,
  "replyCommentTotal": 0,
  "uid": "6744845623167599621",
  "uniqueId": "mandielambeth67",
  "avatarThumbnail": "https://p16-sign-va.tiktokcdn.com/tos-maliva-avt-0068/d763817493ae5e4fcb9d869e39fdf6d7~c5_100x100.jpg?lk3s=30310797&nonce=91691&refresh_token=80f401c80c1759959ae331293d31ba92&x-expires=1737212400&x-signature=JJ%2FZxaXmzeTprpzM9l3iMRfMl4Q%3D&shp=30310797&shcp=-"
},
{
  "videoWebUrl": "https://www.tiktok.com/@itsme_lisap/video/7394107845135928619",
  "submittedVideoUrl": "https://www.tiktok.com/@itsme_lisap/video/7394107845135928619",
  "cid": "7394140194569831214",
  "createTime": 1721582448,
  "createTimeISO": "2024-07-21T17:20:48.000Z",
  "text": "Everyday we get notifications. Multiple times a day. They killed that baby",
  "diggCount": 1,
  "repliesToId": null,
  "replyCommentTotal": 0,
  "uid": "6913932401858397190",
  "uniqueId": "ravenskye86",
  "avatarThumbnail": "https://p16-pu-sign-useast8.tiktokcdn-us.com/tos-useast5-avt-0068-tx/f4ca78cd2afdba6cc79020825f8808ff~c5_100x100.jpg?lk3s=30310797&nonce=86402&refresh_token=6fc020a0704dcb132d9c61391d3e82bf&x-expires=1737212400&x-signature=yZMrMAEKvGT32S6CyX8wuSwB7%2Fc%3D&shp=30310797&shcp=-"
},
{
  "videoWebUrl": "https://www.tiktok.com/@itsme_lisap/video/7394107845135928619",
  "submittedVideoUrl": "https://www.tiktok.com/@itsme_lisap/video/7394107845135928619",
  "cid": "7394117042528125742",
  "createTime": 1721577074,
  "createTimeISO": "2024-07-21T15:51:14.000Z",
  "text": "And then do a go fund me??? No way you caused this",
  "diggCount": 1,
  "repliesToId": null,
  "replyCommentTotal": 0,
  "uid": "6666574096635183109",
  "uniqueId": "someoneyounew",
  "avatarThumbnail": "https://p16-pu-sign-useast8.tiktokcdn-us.com/tos-useast5-avt-0068-tx/01f0c125e4f0f2a44d24b1ddb5709c40~c5_100x100.jpg?lk3s=30310797&nonce=55560&refresh_token=3935d81165c1886f72f9e9121890ea84&x-expires=1737212400&x-signature=kQ4oS5XawXw5Do5NKshg9%2F6Omoc%3D&shp=30310797&shcp=-"
},
{
  "videoWebUrl": "https://www.tiktok.com/@itsme_lisap/video/7394107845135928619",
  "submittedVideoUrl": "https://www.tiktok.com/@itsme_lisap/video/7394107845135928619",
  "cid": "7399291671110501163",
  "createTime": 1722781929,
  "createTimeISO": "2024-08-04T14:32:09.000Z",
  "text": "The parents should be charged with negligent homicide 🚨 They CHOSE to be outside during the 120-degree weather and their daughter tragically paid the price for her parents’ DECISION to go boating.",
  "diggCount": 0,
  "repliesToId": null,
  "replyCommentTotal": 0,
  "uid": "7079068295147914282",
  "uniqueId": "tobinlv",
  "avatarThumbnail": "https://p19-pu-sign-useast8.tiktokcdn-us.com/tos-useast5-avt-0068-tx/22eb7c3fd8cad8d22bfb831822b276a1~c5_100x100.jpg?lk3s=30310797&nonce=11159&refresh_token=044694426f926dfc20ca67aee03d4b46&x-expires=1737212400&x-signature=Ev8of3vTmB3oZ5%2BPSbOqM4nxXUo%3D&shp=30310797&shcp=-"
},
{
  "videoWebUrl": "https://www.tiktok.com/@itsme_lisap/video/7394107845135928619",
  "submittedVideoUrl": "https://www.tiktok.com/@itsme_lisap/video/7394107845135928619",
  "cid": "7396045546606068522",
  "createTime": 1722026097,
  "createTimeISO": "2024-07-26T20:34:57.000Z",
  "text": "I just wanna know how they aren’t being charged how is this any different than a parent leaving a child in a hot car I just don’t see it. Then they were able to leech 50k from ppl",
  "diggCount": 0,
  "repliesToId": null,
  "replyCommentTotal": 0,
  "uid": "6798221044399637509",
  "uniqueId": "illfollowyouintothedark",
  "avatarThumbnail": "https://p19-pu-sign-useast8.tiktokcdn-us.com/tos-useast5-avt-0068-tx/e691598c4dc3261ba6f6b4c9686f3075~c5_100x100.jpg?lk3s=30310797&nonce=72851&refresh_token=661fe2cb35b9c6c1430556dd606ae58f&x-expires=1737212400&x-signature=s%2BEkonjaye7jPHr7PkFnzfflBRY%3D&shp=30310797&shcp=-"
},
{
  "videoWebUrl": "https://www.tiktok.com/@itsme_lisap/video/7394107845135928619",
  "submittedVideoUrl": "https://www.tiktok.com/@itsme_lisap/video/7394107845135928619",
  "cid": "7413373096113193760",
  "createTime": 1726060438,
  "createTimeISO": "2024-09-11T13:13:58.000Z",
  "text": "They deserve PRISON",
  "diggCount": 0,
  "repliesToId": null,
  "replyCommentTotal": 0,
  "uid": "6729106968630543366",
  "uniqueId": "poppyrose012",
  "avatarThumbnail": "https://p16-sign-va.tiktokcdn.com/tos-maliva-avt-0068/7310585391566815237~c5_100x100.jpg?lk3s=30310797&nonce=85965&refresh_token=4f65e8386642f16f0cbc6670c66f5f07&x-expires=1737212400&x-signature=DwZRPInCq%2BdbT%2B1KIgRiCc5J30Y%3D&shp=30310797&shcp=-"
},
{
  "videoWebUrl": "https://www.tiktok.com/@itsme_lisap/video/7394107845135928619",
  "submittedVideoUrl": "https://www.tiktok.com/@itsme_lisap/video/7394107845135928619",
  "cid": "7394967497432253226",
  "createTime": 1721775073,
  "createTimeISO": "2024-07-23T22:51:13.000Z",
  "text": "They live near me, I know their type and they thought they knew better than the heat advisory. They were drunk in the water while baby was on the boat. They deserve charges, but he’s a COP!",
  "diggCount": 0,
  "repliesToId": null,
  "replyCommentTotal": 1,
  "uid": "6746371246335919110",
  "uniqueId": "gigisicilian",
  "avatarThumbnail": "https://p16-sign-va.tiktokcdn.com/tos-maliva-avt-0068/d02fee39af5eaa9c8780901822514023~c5_100x100.jpg?lk3s=30310797&nonce=43774&refresh_token=d5d41e8db3eb3b9b6d698dc056211987&x-expires=1737212400&x-signature=M9G0CL2TxDaHpLEZRyBohf%2BIr5A%3D&shp=30310797&shcp=-"
},
{
  "videoWebUrl": "https://www.tiktok.com/@itsme_lisap/video/7394107845135928619",
  "submittedVideoUrl": "https://www.tiktok.com/@itsme_lisap/video/7394107845135928619",
  "cid": "7394259852669944607",
  "createTime": 1721610306,
  "createTimeISO": "2024-07-22T01:05:06.000Z",
  "text": "Everything that happened that day was a conscious choice made by those parents. Their child died due to their negligence and their choices alone. This wasn’t an accidental tragedy. They did this!",
  "diggCount": 0,
  "repliesToId": null,
  "replyCommentTotal": 1,
  "uid": "6963750978400355333",
  "uniqueId": "kaciix89",
  "avatarThumbnail": "https://p16-sign-va.tiktokcdn.com/tos-maliva-avt-0068/86e5631696ed5dde07aa764b929be581~c5_100x100.jpg?lk3s=30310797&nonce=81084&refresh_token=5e099c06bacdc625fc3fdcafd96ba7d9&x-expires=1737212400&x-signature=QqY749phLEvqFxuGV%2B94szZRpLg%3D&shp=30310797&shcp=-"
},
{
  "videoWebUrl": "https://www.tiktok.com/@itsme_lisap/video/7394107845135928619",
  "submittedVideoUrl": "https://www.tiktok.com/@itsme_lisap/video/7394107845135928619",
  "cid": "7411795194586202885",
  "createTime": 1725693055,
  "createTimeISO": "2024-09-07T07:10:55.000Z",
  "text": "It could of been avoidable but this is about selfish behaviour of the parents",
  "diggCount": 0,
  "repliesToId": null,
  "replyCommentTotal": 0,
  "uid": "7358946729456534533",
  "uniqueId": "nostiffsocksalllwed",
  "avatarThumbnail": "https://p16-sign-va.tiktokcdn.com/tos-maliva-avt-0068/7f8dcb0ea9891eefb3a27d0669891afa~c5_100x100.jpg?lk3s=30310797&nonce=11589&refresh_token=96299a03019d7b609d588128f8828ae8&x-expires=1737212400&x-signature=2LYqWvxNlOgFDEgQbHBWrjTuXQg%3D&shp=30310797&shcp=-"
},
{
  "videoWebUrl": "https://www.tiktok.com/@itsme_lisap/video/7394107845135928619",
  "submittedVideoUrl": "https://www.tiktok.com/@itsme_lisap/video/7394107845135928619",
  "cid": "7406060731646575366",
  "createTime": 1724357895,
  "createTimeISO": "2024-08-22T20:18:15.000Z",
  "text": "I saw 2 kids on picture not the first , plus you need to get back on the boat to get drinks , father is a law enforcement he knows more and boat and alcohol .. ??? It’s weird",
  "diggCount": 0,
  "repliesToId": null,
  "replyCommentTotal": 0,
  "uid": "6944912345173083142",
  "uniqueId": "melilily_",
  "avatarThumbnail": "https://p16-sign-va.tiktokcdn.com/tos-maliva-avt-0068/bca7eed66535f6b848645c386ad7d529~c5_100x100.jpg?lk3s=30310797&nonce=24219&refresh_token=c3250b4614db60cc3fb6af52d144763d&x-expires=1737212400&x-signature=5YSWd7nf9thAYXF9PJJ2MFqpFZA%3D&shp=30310797&shcp=-"
},
{
  "videoWebUrl": "https://www.tiktok.com/@itsme_lisap/video/7394107845135928619",
  "submittedVideoUrl": "https://www.tiktok.com/@itsme_lisap/video/7394107845135928619",
  "cid": "7394855159047799598",
  "createTime": 1721748906,
  "createTimeISO": "2024-07-23T15:35:06.000Z",
  "text": "hes a cop in cali where we break windows for kids an dogs they knew better",
  "diggCount": 0,
  "repliesToId": null,
  "replyCommentTotal": 0,
  "uid": "7306224983834559531",
  "uniqueId": "caffeineanchaos",
  "avatarThumbnail": "https://p16-pu-sign-useast8.tiktokcdn-us.com/tos-useast5-avt-0068-tx/69a7769900ba694f1da571549b302195~c5_100x100.jpg?lk3s=30310797&nonce=8980&refresh_token=f5735800b3b1a7ef78e2b8d284e92db3&x-expires=1737212400&x-signature=3adhWqRLPsaZDL%2F7BR9y%2BSsK5sU%3D&shp=30310797&shcp=-"
},
{
  "videoWebUrl": "https://www.tiktok.com/@itsme_lisap/video/7394107845135928619",
  "submittedVideoUrl": "https://www.tiktok.com/@itsme_lisap/video/7394107845135928619",
  "cid": "7394534713229574955",
  "createTime": 1721674323,
  "createTimeISO": "2024-07-22T18:52:03.000Z",
  "text": "Absolutely disgusting. And he's a cop. They endangered the welfare of that poor baby and she died because of it. They absolutely deserve prison.",
  "diggCount": 0,
  "repliesToId": null,
  "replyCommentTotal": 0,
  "uid": "6793462623143216134",
  "uniqueId": "brwnsugr00",
  "avatarThumbnail": "https://p16-sign-va.tiktokcdn.com/tos-maliva-avt-0068/80a049789334a43a51afd0bce8d672e5~c5_100x100.jpg?lk3s=30310797&nonce=12361&refresh_token=4d84736c39b2e9cccf6d11a0684bd4f9&x-expires=1737212400&x-signature=F4YTQHHaFGLTsPssTa%2Bytee6Td4%3D&shp=30310797&shcp=-"
},
{
  "videoWebUrl": "https://www.tiktok.com/@itsme_lisap/video/7394107845135928619",
  "submittedVideoUrl": "https://www.tiktok.com/@itsme_lisap/video/7394107845135928619",
  "cid": "7394434423994008321",
  "createTime": 1721650954,
  "createTimeISO": "2024-07-22T12:22:34.000Z",
  "text": "💯they need to be trailed as murder they just didn’t care",
  "diggCount": 0,
  "repliesToId": null,
  "replyCommentTotal": 0,
  "uid": "6971820119102391302",
  "uniqueId": "keelyjaynenoonan",
  "avatarThumbnail": "https://p16-sign-sg.tiktokcdn.com/aweme/100x100/tos-alisg-avt-0068/7334068980803436545.jpg?lk3s=30310797&nonce=19115&refresh_token=c3f0ce3d5c827cc00544ea80f7f6b53b&x-expires=1737212400&x-signature=URqcPhlnRH4I3HvPnIs1Pzn7S7U%3D&shp=30310797&shcp=-"
},
{
  "videoWebUrl": "https://www.tiktok.com/@itsme_lisap/video/7394107845135928619",
  "submittedVideoUrl": "https://www.tiktok.com/@itsme_lisap/video/7394107845135928619",
  "cid": "7394304743785595678",
  "createTime": 1721620759,
  "createTimeISO": "2024-07-22T03:59:19.000Z",
  "text": "This isn't their first baby. They have a toddler as well",
  "diggCount": 0,
  "repliesToId": null,
  "replyCommentTotal": 0,
  "uid": "6812791817735865349",
  "uniqueId": "fricken..chicken",
  "avatarThumbnail": "https://p16-sign-va.tiktokcdn.com/tos-maliva-avt-0068/6b0ac033497d00164e443219ac824bcb~c5_100x100.jpg?lk3s=30310797&nonce=33561&refresh_token=076907b85465a93b3d0d3eb2491b2652&x-expires=1737212400&x-signature=rylsuil4MwO8so8bz%2F%2FMtF2feoQ%3D&shp=30310797&shcp=-"
},
{
  "videoWebUrl": "https://www.tiktok.com/@itsme_lisap/video/7394107845135928619",
  "submittedVideoUrl": "https://www.tiktok.com/@itsme_lisap/video/7394107845135928619",
  "cid": "7396378911942558494",
  "createTime": 1722103683,
  "createTimeISO": "2024-07-27T18:08:03.000Z",
  "text": "I definitely treat my dogs better than they treated that baby. I have a cooling towel and I’m looking into buying cooling vest for my dogs",
  "diggCount": 0,
  "repliesToId": null,
  "replyCommentTotal": 0,
  "uid": "6899568567336633350",
  "uniqueId": "capecodstepmom",
  "avatarThumbnail": "https://p16-sign-va.tiktokcdn.com/tos-maliva-avt-0068/7330748646398525445~c5_100x100.jpg?lk3s=30310797&nonce=27412&refresh_token=b0beb7a46b7ba300d0f298829868c653&x-expires=1737212400&x-signature=gLNjdGUiPP36uSgQU%2BEfe909Xm0%3D&shp=30310797&shcp=-"
},
{
  "videoWebUrl": "https://www.tiktok.com/@itsme_lisap/video/7394107845135928619",
  "submittedVideoUrl": "https://www.tiktok.com/@itsme_lisap/video/7394107845135928619",
  "cid": "7394287419002831647",
  "createTime": 1721616721,
  "createTimeISO": "2024-07-22T02:52:01.000Z",
  "text": "Selfish, selfish, awful people! I had both my babies in the summer, 1 in June and 1 July 1st and I sat at home with my babies both times because it was too hot outdoors for them!",
  "diggCount": 0,
  "repliesToId": null,
  "replyCommentTotal": 0,
  "uid": "6996525222308381702",
  "uniqueId": "harperdonovan906",
  "avatarThumbnail": "https://p16-sign-va.tiktokcdn.com/tos-maliva-avt-0068/7329860272542220293~c5_100x100.jpg?lk3s=30310797&nonce=52473&refresh_token=010d01a9b6cf0c189379b1e2440bd0ab&x-expires=1737212400&x-signature=Jw9dYFmqDS3rJ1XnGVWcvEkF4gA%3D&shp=30310797&shcp=-"
},
{
  "videoWebUrl": "https://www.tiktok.com/@itsme_lisap/video/7394107845135928619",
  "submittedVideoUrl": "https://www.tiktok.com/@itsme_lisap/video/7394107845135928619",
  "cid": "7394273302846210858",
  "createTime": 1721613440,
  "createTimeISO": "2024-07-22T01:57:20.000Z",
  "text": "U know what I have NOT done in the last 7yrs since being a mom 3x? Leaving my baby/kid anywhere I am not. U don’t get to “have fun” being a mom to small kids.",
  "diggCount": 0,
  "repliesToId": null,
  "replyCommentTotal": 0,
  "uid": "6996434335310021638",
  "uniqueId": "realestatemamma3",
  "avatarThumbnail": "https://p19-pu-sign-useast8.tiktokcdn-us.com/tos-useast5-avt-0068-tx/354f1011cb1faddaa1d0fb8603ae4cb1~c5_100x100.jpg?lk3s=30310797&nonce=39625&refresh_token=28a3d7087a68995b0600c41fe490faf6&x-expires=1737212400&x-signature=Jl9Hn7dgSlaEL0V5Hh6ND2ApkQ0%3D&shp=30310797&shcp=-"
},
{
  "videoWebUrl": "https://www.tiktok.com/@itsme_lisap/video/7394107845135928619",
  "submittedVideoUrl": "https://www.tiktok.com/@itsme_lisap/video/7394107845135928619",
  "cid": "7394293387367645995",
  "createTime": 1721618117,
  "createTimeISO": "2024-07-22T03:15:17.000Z",
  "text": "We live in coastal SC and have not spent a single day at the beach this year because we have a 6 month old! It’s to hot for her so we find fun indoor activities for our 5 year old",
  "diggCount": 0,
  "repliesToId": null,
  "replyCommentTotal": 0,
  "uid": "6748621321566061573",
  "uniqueId": "pumpingwithamber",
  "avatarThumbnail": "https://p16-pu-sign-useast8.tiktokcdn-us.com/tos-useast5-avt-0068-tx/7351646857208004651~c5_100x100.jpg?lk3s=30310797&nonce=70568&refresh_token=b9ee6d1981e31a206f1ac9125c28dbc7&x-expires=1737212400&x-signature=ZNrZMbGl7mifB1sqvaC88KeKkMs%3D&shp=30310797&shcp=-"
},
{
  "videoWebUrl": "https://www.tiktok.com/@itsme_lisap/video/7394107845135928619",
  "submittedVideoUrl": "https://www.tiktok.com/@itsme_lisap/video/7394107845135928619",
  "cid": "7402357585486201630",
  "createTime": 1723495688,
  "createTimeISO": "2024-08-12T20:48:08.000Z",
  "text": "ARE THEY IN JAIL YET!??? The other Az dad is and for murder!!! Entitled",
  "diggCount": 0,
  "repliesToId": null,
  "replyCommentTotal": 0,
  "uid": "6938752390515819525",
  "uniqueId": "sallymontesdeoca",
  "avatarThumbnail": "https://p16-sign-va.tiktokcdn.com/tos-maliva-avt-0068/7322066703658483718~c5_100x100.jpg?lk3s=30310797&nonce=13729&refresh_token=0653b0d89673b6f6025e0e079f2c4f98&x-expires=1737212400&x-signature=eFveeG7fG4YkMKVB%2FvZLrpG2UOw%3D&shp=30310797&shcp=-"
},
{
  "videoWebUrl": "https://www.tiktok.com/@itsme_lisap/video/7394107845135928619",
  "submittedVideoUrl": "https://www.tiktok.com/@itsme_lisap/video/7394107845135928619",
  "cid": "7394235436950471466",
  "createTime": 1721604623,
  "createTimeISO": "2024-07-21T23:30:23.000Z",
  "text": "If you all only knew the amount of neglect that is so heartbreakingly common for kids. As a teacher I saw it so much. 💯 Negligence & it's 💯 ABUSE.",
  "diggCount": 0,
  "repliesToId": null,
  "replyCommentTotal": 0,
  "uid": "6817980839244235782",
  "uniqueId": "melancholyandpetrichor",
  "avatarThumbnail": "https://p16-pu-sign-useast8.tiktokcdn-us.com/tos-useast5-avt-0068-tx/f33110b67c2bdc1099e2adfe78296fc7~c5_100x100.jpg?lk3s=30310797&nonce=71692&refresh_token=ebea742d8605e541a3eeef1f756e92cb&x-expires=1737212400&x-signature=Xd8OGVs8TFuQt6pPHh4HO3%2B1I4w%3D&shp=30310797&shcp=-"
},
{
  "videoWebUrl": "https://www.tiktok.com/@itsme_lisap/video/7394107845135928619",
  "submittedVideoUrl": "https://www.tiktok.com/@itsme_lisap/video/7394107845135928619",
  "cid": "7394219299781133062",
  "createTime": 1721600862,
  "createTimeISO": "2024-07-21T22:27:42.000Z",
  "text": "I don’t even party for new years anymore or other holidays that could stress my dog. A parents duty is the health and well-being of their child. Infuriating and heartbreaking",
  "diggCount": 0,
  "repliesToId": null,
  "replyCommentTotal": 0,
  "uid": "6813015182538376198",
  "uniqueId": "nick_storm",
  "avatarThumbnail": "https://p16-sign-va.tiktokcdn.com/tos-maliva-avt-0068/91d1215123a3703e64d44d9a3e18524e~c5_100x100.jpg?lk3s=30310797&nonce=51994&refresh_token=2bafebebcbe8a40ba49ff6758f88c5e4&x-expires=1737212400&x-signature=PzITCIsAvP5RDK4VNMKf2EiXuHs%3D&shp=30310797&shcp=-"
},
{
  "videoWebUrl": "https://www.tiktok.com/@itsme_lisap/video/7394107845135928619",
  "submittedVideoUrl": "https://www.tiktok.com/@itsme_lisap/video/7394107845135928619",
  "cid": "7394352706900624170",
  "createTime": 1721631943,
  "createTimeISO": "2024-07-22T07:05:43.000Z",
  "text": "My God we were up at McCall on a lake in 90 degree heat, I watched a mother carrying her baby in a pack WITH protection on its head. I literally had an anxiety attack. WTF.",
  "diggCount": 0,
  "repliesToId": null,
  "replyCommentTotal": 0,
  "uid": "6807415922271224838",
  "uniqueId": "boisehomes",
  "avatarThumbnail": "https://p19-pu-sign-useast8.tiktokcdn-us.com/tos-useast5-avt-0068-tx/e4413c758ea767c9a8ec737396215106~c5_100x100.jpg?lk3s=30310797&nonce=83906&refresh_token=00bdeda1b049ec72856768b70deefa81&x-expires=1737212400&x-signature=nR8PFOk3lbvIkUx6iHUd%2FhS4RDY%3D&shp=30310797&shcp=-"
},
{
  "videoWebUrl": "https://www.tiktok.com/@itsme_lisap/video/7394107845135928619",
  "submittedVideoUrl": "https://www.tiktok.com/@itsme_lisap/video/7394107845135928619",
  "cid": "7395664257231635230",
  "createTime": 1721937295,
  "createTimeISO": "2024-07-25T19:54:55.000Z",
  "text": "6 months to a year bubble. The fact that babies that young shouldn’t even really have sun block on, so keep them inside 😭😭 You miss 1 year. Get over it.",
  "diggCount": 0,
  "repliesToId": null,
  "replyCommentTotal": 0,
  "uid": "6897375579793441797",
  "uniqueId": "jenwith1n_soberadhdvers",
  "avatarThumbnail": "https://p16-sign.tiktokcdn-us.com/tos-useast5-avt-0068-tx/7347522080243941418~c5_100x100.jpg?lk3s=30310797&nonce=65432&refresh_token=1d8aa635beba2bf7b51da36e64511f5f&x-expires=1737212400&x-signature=qAKfZvXCjNuZO8wVEiTcsrFiOag%3D&shp=30310797&shcp=-"
},
{
  "videoWebUrl": "https://www.tiktok.com/@itsme_lisap/video/7394107845135928619",
  "submittedVideoUrl": "https://www.tiktok.com/@itsme_lisap/video/7394107845135928619",
  "cid": "7395203877715067679",
  "createTime": 1721830121,
  "createTimeISO": "2024-07-24T14:08:41.000Z",
  "text": "They need to charge them for this babies death. How TF are you going to put in risk your child’s life for your own fun?",
  "diggCount": 0,
  "repliesToId": null,
  "replyCommentTotal": 0,
  "uid": "6746051310619280390",
  "uniqueId": "cooking.with.a1",
  "avatarThumbnail": "https://p19-pu-sign-useast8.tiktokcdn-us.com/tos-useast8-avt-0068-tx2/ec630391fec59c87728e7a125cd9b51f~c5_100x100.jpg?lk3s=30310797&nonce=88175&refresh_token=d6ac8e9cd43b63f2028135f5e793a247&x-expires=1737212400&x-signature=UU4nT1yFTrHrZF8FUyXbNgaX97c%3D&shp=30310797&shcp=-"
},
{
  "videoWebUrl": "https://www.tiktok.com/@itsme_lisap/video/7394107845135928619",
  "submittedVideoUrl": "https://www.tiktok.com/@itsme_lisap/video/7394107845135928619",
  "cid": "7400401596116960030",
  "createTime": 1723040276,
  "createTimeISO": "2024-08-07T14:17:56.000Z",
  "text": "The poor baby, quite literally boiled alive. My friend is in court right now because her kid walked out of the hotel room. But these killers are good to go?",
  "diggCount": 0,
  "repliesToId": null,
  "replyCommentTotal": 0,
  "uid": "6930095968475300869",
  "uniqueId": "thirtythreeacres",
  "avatarThumbnail": "https://p19-pu-sign-useast8.tiktokcdn-us.com/tos-useast5-avt-0068-tx/79e230c52f2092e30040319cd25ae9a3~c5_100x100.jpg?lk3s=30310797&nonce=13852&refresh_token=4b7ea267e9f13c781c1f8c6d33b0f833&x-expires=1737212400&x-signature=V%2BP4Qiriwrbb6tIQYFflOVajP0c%3D&shp=30310797&shcp=-"
},
{
  "videoWebUrl": "https://www.tiktok.com/@itsme_lisap/video/7394107845135928619",
  "submittedVideoUrl": "https://www.tiktok.com/@itsme_lisap/video/7394107845135928619",
  "cid": "7398744820469220127",
  "createTime": 1722654523,
  "createTimeISO": "2024-08-03T03:08:43.000Z",
  "text": "The fact that they got 50,000$ from the gofundme",
  "diggCount": 0,
  "repliesToId": null,
  "replyCommentTotal": 0,
  "uid": "75993272761917440",
  "uniqueId": "krazyk00luv",
  "avatarThumbnail": "https://p16-pu-sign-useast8.tiktokcdn-us.com/tos-useast5-avt-0068-tx/7351363991874043946~c5_100x100.jpg?lk3s=30310797&nonce=55067&refresh_token=5395a211025007dd34f888b7d84648ee&x-expires=1737212400&x-signature=bLIi%2FCJoqfG41GLraHoSLEYdxh8%3D&shp=30310797&shcp=-"
},
{
  "videoWebUrl": "https://www.tiktok.com/@itsme_lisap/video/7394107845135928619",
  "submittedVideoUrl": "https://www.tiktok.com/@itsme_lisap/video/7394107845135928619",
  "cid": "7395064581733516062",
  "createTime": 1721797679,
  "createTimeISO": "2024-07-24T05:07:59.000Z",
  "text": "The fact that the mom is an \"influencer\" and the dad is a cop tells me everything I need to know. Also that lake is a notorious party place. They dngaf and then had the audacity to start a GFM",
  "diggCount": 0,
  "repliesToId": null,
  "replyCommentTotal": 0,
  "uid": "7242910629450728490",
  "uniqueId": "lmariew1",
  "avatarThumbnail": "https://p19-sign.tiktokcdn-us.com/tos-useast5-avt-0068-tx/0ce0c535015bf3a1aa070a9fde5d969e~c5_100x100.jpg?lk3s=30310797&nonce=73447&refresh_token=a732f55aaf02ad6ca3d51915027f2774&x-expires=1737212400&x-signature=xZcXUNeULchhfH5TWKPlN7SAZyM%3D&shp=30310797&shcp=-"
}]