[{
  "videoWebUrl": "https://www.tiktok.com/@jenbrallier/video/7446543600827075886",
  "submittedVideoUrl": "https://www.tiktok.com/@jenbrallier/video/7446543600827075886",
  "cid": "7446545276494660383",
  "createTime": 1733783945,
  "createTimeISO": "2024-12-09T22:39:05.000Z",
  "text": "This was so fun to watch!! Super happy for you Jen❤️❤️",
  "diggCount": 1,
  "repliesToId": null,
  "replyCommentTotal": 1,
  "uid": "6994450906604864517",
  "uniqueId": "crownsofglory",
  "avatarThumbnail": "https://p19-pu-sign-useast8.tiktokcdn-us.com/tos-useast8-avt-0068-tx2/533dc6066f1ec244accfb6a534c7f3e7~c5_100x100.jpg?lk3s=30310797&nonce=3776&refresh_token=548b63788ab49030fecc51a689eac1d4&x-expires=1736928000&x-signature=WmQGtQfHHHEBPh%2B%2BS4OF0T03inE%3D&shp=30310797&shcp=-"
},
{
  "videoWebUrl": "https://www.tiktok.com/@jenbrallier/video/7446543600827075886",
  "submittedVideoUrl": "https://www.tiktok.com/@jenbrallier/video/7446543600827075886",
  "cid": "7446546988252791595",
  "createTime": 1733784344,
  "createTimeISO": "2024-12-09T22:45:44.000Z",
  "text": "Thank you 🥹🥹",
  "diggCount": 0,
  "repliesToId": "7446545276494660383",
  "replyCommentTotal": null,
  "uid": "6845086536640431109",
  "uniqueId": "jenbrallier",
  "avatarThumbnail": "https://p19-pu-sign-useast8.tiktokcdn-us.com/tos-useast5-avt-0068-tx/5bd71e5e714fdd62cbdedd74525a27c0~c5_100x100.jpg?lk3s=30310797&nonce=83284&refresh_token=0a572d4907f0a6a3341e7f073753fadd&x-expires=1736928000&x-signature=SYriC6ds3z9PNXN%2FWFuJF5csF6A%3D&shp=30310797&shcp=-"
},
{
  "videoWebUrl": "https://www.tiktok.com/@jenbrallier/video/7446543600827075886",
  "submittedVideoUrl": "https://www.tiktok.com/@jenbrallier/video/7446543600827075886",
  "cid": "7447006468825367342",
  "createTime": 1733891337,
  "createTimeISO": "2024-12-11T04:28:57.000Z",
  "text": "I live in Columbus and really enjoy watching yours and Deans content! So wish you would come back with him :) The North Market is amazing! Come back soon",
  "diggCount": 1,
  "repliesToId": null,
  "replyCommentTotal": 0,
  "uid": "6904530462820074502",
  "uniqueId": "juliejules47s",
  "avatarThumbnail": "https://p16-pu-sign-useast8.tiktokcdn-us.com/tos-useast5-avt-0068-tx/585033a72a342f415bb6fba4f67ced03~c5_100x100.jpg?lk3s=30310797&nonce=17930&refresh_token=d4bfadb68fd979463c5e29b92d885ca7&x-expires=1736928000&x-signature=X3OOVsm%2FkkC%2BUwcQ0X%2FnMndqNbw%3D&shp=30310797&shcp=-"
}]